{
    "version": "0.4",
    "title": "Block &#8211; team block on the pictures",
    "type": "section",
    "metadata": {
        "template_type": "section-team",
        "include_in_zip": "1",
        "elementor_pro_required": null,
        "wp_page_template": "elementor_canvas"
    },
    "content": [
        {
            "id": "7fca78cf",
            "settings": {
                "content_width": {
                    "unit": "px",
                    "size": 1170,
                    "sizes": []
                },
                "background_background": "classic",
                "background_color": "#FFFFFF",
                "margin": {
                    "unit": "px",
                    "top": "0",
                    "right": 0,
                    "bottom": "0",
                    "left": 0,
                    "isLinked": false
                },
                "margin_tablet": {
                    "unit": "px",
                    "top": "0",
                    "right": 0,
                    "bottom": "0",
                    "left": 0,
                    "isLinked": false
                },
                "margin_mobile": {
                    "unit": "px",
                    "top": "0",
                    "right": 0,
                    "bottom": "0",
                    "left": 0,
                    "isLinked": false
                },
                "padding": {
                    "unit": "px",
                    "top": "161",
                    "right": "30",
                    "bottom": "212",
                    "left": "30",
                    "isLinked": false
                },
                "padding_tablet": {
                    "unit": "px",
                    "top": "100",
                    "right": "30",
                    "bottom": "109",
                    "left": "30",
                    "isLinked": false
                },
                "padding_mobile": {
                    "unit": "px",
                    "top": "60",
                    "right": "20",
                    "bottom": "60",
                    "left": "20",
                    "isLinked": false
                }
            },
            "elements": [
                {
                    "id": "6635436",
                    "settings": {
                        "_column_size": 100,
                        "_inline_size": null,
                        "space_between_widgets": 0,
                        "margin": {
                            "unit": "px",
                            "top": "0",
                            "right": "0",
                            "bottom": "0",
                            "left": "0",
                            "isLinked": false
                        },
                        "padding": {
                            "unit": "px",
                            "top": "0",
                            "right": "0",
                            "bottom": "0",
                            "left": "0",
                            "isLinked": false
                        }
                    },
                    "elements": [
                        {
                            "id": "201b8e09",
                            "settings": {
                                "title": "Have Creative Projects?",
                                "header_size": "h3",
                                "align": "center",
                                "title_color": "#E93314",
                                "typography_typography": "custom",
                                "typography_font_family": "Josefin Sans",
                                "typography_font_size": {
                                    "unit": "em",
                                    "size": 1.111,
                                    "sizes": []
                                },
                                "typography_font_weight": "600",
                                "typography_text_transform": "none",
                                "typography_font_style": "normal",
                                "typography_text_decoration": "none",
                                "typography_line_height": {
                                    "unit": "em",
                                    "size": 1,
                                    "sizes": []
                                },
                                "typography_letter_spacing": {
                                    "unit": "px",
                                    "size": 0,
                                    "sizes": []
                                },
                                "_margin": {
                                    "unit": "px",
                                    "top": "0",
                                    "right": "0",
                                    "bottom": "0",
                                    "left": "0",
                                    "isLinked": false
                                },
                                "_padding": {
                                    "unit": "px",
                                    "top": "0",
                                    "right": "0",
                                    "bottom": "0",
                                    "left": "0",
                                    "isLinked": false
                                },
                                "_animation": "fadeIn",
                                "animation_duration": "fast"
                            },
                            "elements": [],
                            "isInner": false,
                            "widgetType": "heading",
                            "elType": "widget"
                        },
                        {
                            "id": "31d31168",
                            "settings": {
                                "title": "We are Digital Studio",
                                "align": "center",
                                "title_color": "#0C0C0C",
                                "typography_typography": "custom",
                                "typography_font_family": "Josefin Sans",
                                "typography_font_size": {
                                    "unit": "em",
                                    "size": 2.778,
                                    "sizes": []
                                },
                                "typography_font_size_tablet": {
                                    "unit": "em",
                                    "size": 2.3,
                                    "sizes": []
                                },
                                "typography_font_size_mobile": {
                                    "unit": "em",
                                    "size": 1.7,
                                    "sizes": []
                                },
                                "typography_font_weight": "600",
                                "typography_text_transform": "none",
                                "typography_font_style": "normal",
                                "typography_text_decoration": "none",
                                "typography_line_height": {
                                    "unit": "em",
                                    "size": 1.2,
                                    "sizes": []
                                },
                                "typography_letter_spacing": {
                                    "unit": "px",
                                    "size": 0,
                                    "sizes": []
                                },
                                "_margin": {
                                    "unit": "px",
                                    "top": "28",
                                    "right": "0",
                                    "bottom": "0",
                                    "left": "0",
                                    "isLinked": false
                                },
                                "_margin_tablet": {
                                    "unit": "px",
                                    "top": "20",
                                    "right": "0",
                                    "bottom": "0",
                                    "left": "0",
                                    "isLinked": false
                                },
                                "_padding": {
                                    "unit": "px",
                                    "top": "0",
                                    "right": "0",
                                    "bottom": "0",
                                    "left": "0",
                                    "isLinked": false
                                },
                                "_padding_tablet": {
                                    "unit": "px",
                                    "top": "0",
                                    "right": "0",
                                    "bottom": "0",
                                    "left": "0",
                                    "isLinked": false
                                },
                                "_animation": "fadeIn",
                                "_margin_mobile": {
                                    "unit": "px",
                                    "top": "20",
                                    "right": "0",
                                    "bottom": "0",
                                    "left": "0",
                                    "isLinked": false
                                },
                                "_padding_mobile": {
                                    "unit": "px",
                                    "top": "0",
                                    "right": "0",
                                    "bottom": "0",
                                    "left": "0",
                                    "isLinked": false
                                },
                                "_animation_delay": 200,
                                "animation_duration": "slow"
                            },
                            "elements": [],
                            "isInner": false,
                            "widgetType": "heading",
                            "elType": "widget"
                        },
                        {
                            "id": "6ae815e3",
                            "settings": {
                                "layout": "full_width",
                                "structure": "30",
                                "margin": {
                                    "unit": "px",
                                    "top": "52",
                                    "right": 0,
                                    "bottom": "0",
                                    "left": 0,
                                    "isLinked": false
                                },
                                "margin_tablet": {
                                    "unit": "px",
                                    "top": "26",
                                    "right": 0,
                                    "bottom": "0",
                                    "left": 0,
                                    "isLinked": false
                                },
                                "margin_mobile": {
                                    "unit": "px",
                                    "top": "19",
                                    "right": 0,
                                    "bottom": "0",
                                    "left": 0,
                                    "isLinked": false
                                },
                                "padding": {
                                    "unit": "px",
                                    "top": "0",
                                    "right": "0",
                                    "bottom": "0",
                                    "left": "0",
                                    "isLinked": false
                                },
                                "padding_tablet": {
                                    "unit": "px",
                                    "top": "0",
                                    "right": "0",
                                    "bottom": "0",
                                    "left": "0",
                                    "isLinked": false
                                }
                            },
                            "elements": [
                                {
                                    "id": "3b7458db",
                                    "settings": {
                                        "_column_size": 33,
                                        "_inline_size": null,
                                        "space_between_widgets": 0,
                                        "background_background": "classic",
                                        "background_image": {
                                            "url": "http:\/\/template-kit.themerex.net\/creative-portfolio\/wp-content\/uploads\/sites\/2\/2020\/02\/amazing-african-curly-young-woman-wearing-yellow-PCUMRSX-unsplash-scaled.jpg",
                                            "id": 4024
                                        },
                                        "background_position": "center center",
                                        "background_repeat": "no-repeat",
                                        "background_size": "cover",
                                        "border_radius": {
                                            "unit": "px",
                                            "top": "8",
                                            "right": "8",
                                            "bottom": "8",
                                            "left": "8",
                                            "isLinked": true
                                        },
                                        "margin": {
                                            "unit": "px",
                                            "top": "0",
                                            "right": "20",
                                            "bottom": "0",
                                            "left": "0",
                                            "isLinked": false
                                        },
                                        "margin_mobile": {
                                            "unit": "px",
                                            "top": "0",
                                            "right": "0",
                                            "bottom": "0",
                                            "left": "0",
                                            "isLinked": false
                                        },
                                        "padding": {
                                            "unit": "px",
                                            "top": "293",
                                            "right": "30",
                                            "bottom": "30",
                                            "left": "30",
                                            "isLinked": false
                                        },
                                        "padding_tablet": {
                                            "unit": "px",
                                            "top": "150",
                                            "right": "20",
                                            "bottom": "20",
                                            "left": "20",
                                            "isLinked": false
                                        },
                                        "animation": "fadeIn"
                                    },
                                    "elements": [
                                        {
                                            "id": "6c08ef6f",
                                            "settings": {
                                                "image": {
                                                    "url": "",
                                                    "id": ""
                                                },
                                                "title_text": "Cheryl Hardy",
                                                "description_text": "Manager",
                                                "title_size": "p",
                                                "title_bottom_space": {
                                                    "unit": "px",
                                                    "size": 10,
                                                    "sizes": []
                                                },
                                                "title_bottom_space_tablet": {
                                                    "unit": "px",
                                                    "size": 8,
                                                    "sizes": []
                                                },
                                                "title_color": "#0D0D12",
                                                "title_typography_typography": "custom",
                                                "title_typography_font_family": "Josefin Sans",
                                                "title_typography_font_size": {
                                                    "unit": "em",
                                                    "size": 1.556,
                                                    "sizes": []
                                                },
                                                "title_typography_font_size_tablet": {
                                                    "unit": "em",
                                                    "size": 1.3,
                                                    "sizes": []
                                                },
                                                "title_typography_font_weight": "600",
                                                "title_typography_text_transform": "none",
                                                "title_typography_font_style": "normal",
                                                "title_typography_text_decoration": "none",
                                                "title_typography_line_height": {
                                                    "unit": "em",
                                                    "size": 1,
                                                    "sizes": []
                                                },
                                                "title_typography_letter_spacing": {
                                                    "unit": "px",
                                                    "size": 0,
                                                    "sizes": []
                                                },
                                                "description_color": "#6D7277",
                                                "description_typography_typography": "custom",
                                                "description_typography_font_family": "Josefin Sans",
                                                "description_typography_font_size": {
                                                    "unit": "em",
                                                    "size": 0.889,
                                                    "sizes": []
                                                },
                                                "description_typography_font_weight": "400",
                                                "description_typography_text_transform": "none",
                                                "description_typography_font_style": "normal",
                                                "description_typography_text_decoration": "none",
                                                "description_typography_line_height": {
                                                    "unit": "em",
                                                    "size": 1,
                                                    "sizes": []
                                                },
                                                "description_typography_letter_spacing": {
                                                    "unit": "px",
                                                    "size": 0,
                                                    "sizes": []
                                                },
                                                "_margin": {
                                                    "unit": "px",
                                                    "top": "0",
                                                    "right": "0",
                                                    "bottom": "0",
                                                    "left": "0",
                                                    "isLinked": false
                                                },
                                                "_margin_tablet": {
                                                    "unit": "px",
                                                    "top": "0",
                                                    "right": "0",
                                                    "bottom": "0",
                                                    "left": "0",
                                                    "isLinked": false
                                                },
                                                "_padding": {
                                                    "unit": "px",
                                                    "top": "24",
                                                    "right": "20",
                                                    "bottom": "21",
                                                    "left": "20",
                                                    "isLinked": false
                                                },
                                                "_padding_tablet": {
                                                    "unit": "px",
                                                    "top": "21",
                                                    "right": "10",
                                                    "bottom": "16",
                                                    "left": "10",
                                                    "isLinked": false
                                                },
                                                "_animation": "fadeIn",
                                                "animation_duration": "slow",
                                                "_animation_delay": 100,
                                                "_background_background": "classic",
                                                "_background_color": "#FFFFFF",
                                                "_background_position": "center center",
                                                "_background_repeat": "no-repeat",
                                                "_background_size": "cover"
                                            },
                                            "elements": [],
                                            "isInner": false,
                                            "widgetType": "image-box",
                                            "elType": "widget"
                                        }
                                    ],
                                    "isInner": true,
                                    "elType": "column"
                                },
                                {
                                    "id": "49bb0131",
                                    "settings": {
                                        "_column_size": 33,
                                        "_inline_size": null,
                                        "space_between_widgets": 0,
                                        "background_background": "classic",
                                        "background_image": {
                                            "url": "http:\/\/template-kit.themerex.net\/creative-portfolio\/wp-content\/uploads\/sites\/2\/2020\/01\/happy-redhead-young-lady-student-reading-book-M5Z7RVC.jpg",
                                            "id": 2712
                                        },
                                        "background_position": "center center",
                                        "background_repeat": "no-repeat",
                                        "background_size": "cover",
                                        "border_radius": {
                                            "unit": "px",
                                            "top": "8",
                                            "right": "8",
                                            "bottom": "8",
                                            "left": "8",
                                            "isLinked": true
                                        },
                                        "margin": {
                                            "unit": "px",
                                            "top": "0",
                                            "right": "10",
                                            "bottom": "0",
                                            "left": "10",
                                            "isLinked": false
                                        },
                                        "margin_mobile": {
                                            "unit": "px",
                                            "top": "20",
                                            "right": "0",
                                            "bottom": "0",
                                            "left": "0",
                                            "isLinked": false
                                        },
                                        "padding": {
                                            "unit": "px",
                                            "top": "293",
                                            "right": "30",
                                            "bottom": "30",
                                            "left": "30",
                                            "isLinked": false
                                        },
                                        "padding_tablet": {
                                            "unit": "px",
                                            "top": "150",
                                            "right": "20",
                                            "bottom": "20",
                                            "left": "20",
                                            "isLinked": false
                                        },
                                        "animation": "fadeIn"
                                    },
                                    "elements": [
                                        {
                                            "id": "747a3665",
                                            "settings": {
                                                "image": {
                                                    "url": "",
                                                    "id": ""
                                                },
                                                "title_text": "Gail Rodgers",
                                                "description_text": "Photographer",
                                                "title_size": "p",
                                                "title_bottom_space": {
                                                    "unit": "px",
                                                    "size": 10,
                                                    "sizes": []
                                                },
                                                "title_bottom_space_tablet": {
                                                    "unit": "px",
                                                    "size": 8,
                                                    "sizes": []
                                                },
                                                "title_color": "#0D0D12",
                                                "title_typography_typography": "custom",
                                                "title_typography_font_family": "Josefin Sans",
                                                "title_typography_font_size": {
                                                    "unit": "em",
                                                    "size": 1.556,
                                                    "sizes": []
                                                },
                                                "title_typography_font_size_tablet": {
                                                    "unit": "em",
                                                    "size": 1.3,
                                                    "sizes": []
                                                },
                                                "title_typography_font_weight": "600",
                                                "title_typography_text_transform": "none",
                                                "title_typography_font_style": "normal",
                                                "title_typography_text_decoration": "none",
                                                "title_typography_line_height": {
                                                    "unit": "em",
                                                    "size": 1,
                                                    "sizes": []
                                                },
                                                "title_typography_letter_spacing": {
                                                    "unit": "px",
                                                    "size": 0,
                                                    "sizes": []
                                                },
                                                "description_color": "#6D7277",
                                                "description_typography_typography": "custom",
                                                "description_typography_font_family": "Josefin Sans",
                                                "description_typography_font_size": {
                                                    "unit": "em",
                                                    "size": 0.889,
                                                    "sizes": []
                                                },
                                                "description_typography_font_weight": "400",
                                                "description_typography_text_transform": "none",
                                                "description_typography_font_style": "normal",
                                                "description_typography_text_decoration": "none",
                                                "description_typography_line_height": {
                                                    "unit": "em",
                                                    "size": 1,
                                                    "sizes": []
                                                },
                                                "description_typography_letter_spacing": {
                                                    "unit": "px",
                                                    "size": 0,
                                                    "sizes": []
                                                },
                                                "_margin": {
                                                    "unit": "px",
                                                    "top": "0",
                                                    "right": "0",
                                                    "bottom": "0",
                                                    "left": "0",
                                                    "isLinked": false
                                                },
                                                "_margin_tablet": {
                                                    "unit": "px",
                                                    "top": "0",
                                                    "right": "0",
                                                    "bottom": "0",
                                                    "left": "0",
                                                    "isLinked": false
                                                },
                                                "_padding": {
                                                    "unit": "px",
                                                    "top": "24",
                                                    "right": "20",
                                                    "bottom": "21",
                                                    "left": "20",
                                                    "isLinked": false
                                                },
                                                "_padding_tablet": {
                                                    "unit": "px",
                                                    "top": "21",
                                                    "right": "10",
                                                    "bottom": "16",
                                                    "left": "10",
                                                    "isLinked": false
                                                },
                                                "_animation": "fadeIn",
                                                "animation_duration": "slow",
                                                "_animation_delay": 100,
                                                "_background_background": "classic",
                                                "_background_color": "#FFFFFF",
                                                "_background_position": "center center",
                                                "_background_repeat": "no-repeat",
                                                "_background_size": "cover"
                                            },
                                            "elements": [],
                                            "isInner": false,
                                            "widgetType": "image-box",
                                            "elType": "widget"
                                        }
                                    ],
                                    "isInner": true,
                                    "elType": "column"
                                },
                                {
                                    "id": "1f27b7df",
                                    "settings": {
                                        "_column_size": 33,
                                        "_inline_size": null,
                                        "space_between_widgets": 0,
                                        "background_background": "classic",
                                        "background_image": {
                                            "url": "http:\/\/template-kit.themerex.net\/creative-portfolio\/wp-content\/uploads\/sites\/2\/2020\/01\/photo-of-happy-european-woman-18-20-with-curly-ZDJ6MN5.jpg",
                                            "id": 2687
                                        },
                                        "background_position": "center center",
                                        "background_repeat": "no-repeat",
                                        "background_size": "cover",
                                        "border_radius": {
                                            "unit": "px",
                                            "top": "8",
                                            "right": "8",
                                            "bottom": "8",
                                            "left": "8",
                                            "isLinked": true
                                        },
                                        "margin": {
                                            "unit": "px",
                                            "top": "0",
                                            "right": "0",
                                            "bottom": "0",
                                            "left": "20",
                                            "isLinked": false
                                        },
                                        "margin_mobile": {
                                            "unit": "px",
                                            "top": "20",
                                            "right": "0",
                                            "bottom": "0",
                                            "left": "0",
                                            "isLinked": false
                                        },
                                        "padding": {
                                            "unit": "px",
                                            "top": "293",
                                            "right": "30",
                                            "bottom": "30",
                                            "left": "30",
                                            "isLinked": false
                                        },
                                        "padding_tablet": {
                                            "unit": "px",
                                            "top": "150",
                                            "right": "20",
                                            "bottom": "20",
                                            "left": "20",
                                            "isLinked": false
                                        },
                                        "animation": "fadeIn"
                                    },
                                    "elements": [
                                        {
                                            "id": "474a6cc0",
                                            "settings": {
                                                "image": {
                                                    "url": "",
                                                    "id": ""
                                                },
                                                "title_text": "Monica Rudd",
                                                "description_text": "Manager",
                                                "title_size": "p",
                                                "title_bottom_space": {
                                                    "unit": "px",
                                                    "size": 10,
                                                    "sizes": []
                                                },
                                                "title_bottom_space_tablet": {
                                                    "unit": "px",
                                                    "size": 8,
                                                    "sizes": []
                                                },
                                                "title_color": "#0D0D12",
                                                "title_typography_typography": "custom",
                                                "title_typography_font_family": "Josefin Sans",
                                                "title_typography_font_size": {
                                                    "unit": "em",
                                                    "size": 1.556,
                                                    "sizes": []
                                                },
                                                "title_typography_font_size_tablet": {
                                                    "unit": "em",
                                                    "size": 1.3,
                                                    "sizes": []
                                                },
                                                "title_typography_font_weight": "600",
                                                "title_typography_text_transform": "none",
                                                "title_typography_font_style": "normal",
                                                "title_typography_text_decoration": "none",
                                                "title_typography_line_height": {
                                                    "unit": "em",
                                                    "size": 1,
                                                    "sizes": []
                                                },
                                                "title_typography_letter_spacing": {
                                                    "unit": "px",
                                                    "size": 0,
                                                    "sizes": []
                                                },
                                                "description_color": "#6D7277",
                                                "description_typography_typography": "custom",
                                                "description_typography_font_family": "Josefin Sans",
                                                "description_typography_font_size": {
                                                    "unit": "em",
                                                    "size": 0.889,
                                                    "sizes": []
                                                },
                                                "description_typography_font_weight": "400",
                                                "description_typography_text_transform": "none",
                                                "description_typography_font_style": "normal",
                                                "description_typography_text_decoration": "none",
                                                "description_typography_line_height": {
                                                    "unit": "em",
                                                    "size": 1,
                                                    "sizes": []
                                                },
                                                "description_typography_letter_spacing": {
                                                    "unit": "px",
                                                    "size": 0,
                                                    "sizes": []
                                                },
                                                "_margin": {
                                                    "unit": "px",
                                                    "top": "0",
                                                    "right": "0",
                                                    "bottom": "0",
                                                    "left": "0",
                                                    "isLinked": false
                                                },
                                                "_margin_tablet": {
                                                    "unit": "px",
                                                    "top": "0",
                                                    "right": "0",
                                                    "bottom": "0",
                                                    "left": "0",
                                                    "isLinked": false
                                                },
                                                "_padding": {
                                                    "unit": "px",
                                                    "top": "24",
                                                    "right": "20",
                                                    "bottom": "21",
                                                    "left": "20",
                                                    "isLinked": false
                                                },
                                                "_padding_tablet": {
                                                    "unit": "px",
                                                    "top": "21",
                                                    "right": "10",
                                                    "bottom": "16",
                                                    "left": "10",
                                                    "isLinked": false
                                                },
                                                "_animation": "fadeIn",
                                                "animation_duration": "slow",
                                                "_animation_delay": 100,
                                                "_background_background": "classic",
                                                "_background_color": "#FFFFFF",
                                                "_background_position": "center center",
                                                "_background_repeat": "no-repeat",
                                                "_background_size": "cover"
                                            },
                                            "elements": [],
                                            "isInner": false,
                                            "widgetType": "image-box",
                                            "elType": "widget"
                                        }
                                    ],
                                    "isInner": true,
                                    "elType": "column"
                                }
                            ],
                            "isInner": true,
                            "elType": "section"
                        }
                    ],
                    "isInner": false,
                    "elType": "column"
                }
            ],
            "isInner": false,
            "elType": "section"
        },
        {
            "id": "5c5c2d6c",
            "settings": {
                "layout": "full_width",
                "background_background": "classic",
                "background_color": "#FFFFFF",
                "margin": {
                    "unit": "px",
                    "top": "0",
                    "right": 0,
                    "bottom": "0",
                    "left": 0,
                    "isLinked": false
                },
                "margin_tablet": {
                    "unit": "px",
                    "top": "0",
                    "right": 0,
                    "bottom": "0",
                    "left": 0,
                    "isLinked": false
                },
                "margin_mobile": {
                    "unit": "px",
                    "top": "0",
                    "right": 0,
                    "bottom": "0",
                    "left": 0,
                    "isLinked": false
                },
                "padding": {
                    "unit": "px",
                    "top": "10",
                    "right": "30",
                    "bottom": "100",
                    "left": "30",
                    "isLinked": false
                },
                "padding_tablet": {
                    "unit": "px",
                    "top": "10",
                    "right": "30",
                    "bottom": "80",
                    "left": "30",
                    "isLinked": false
                },
                "padding_mobile": {
                    "unit": "px",
                    "top": "40",
                    "right": "20",
                    "bottom": "60",
                    "left": "20",
                    "isLinked": false
                }
            },
            "elements": [
                {
                    "id": "3b61b293",
                    "settings": {
                        "_column_size": 100,
                        "_inline_size": null,
                        "space_between_widgets": 0,
                        "margin": {
                            "unit": "px",
                            "top": "0",
                            "right": "0",
                            "bottom": "0",
                            "left": "0",
                            "isLinked": false
                        },
                        "padding": {
                            "unit": "px",
                            "top": "0",
                            "right": "0",
                            "bottom": "0",
                            "left": "0",
                            "isLinked": false
                        }
                    },
                    "elements": [
                        {
                            "id": "1f457ce5",
                            "settings": {
                                "title": "Template - team block on the pictures",
                                "header_size": "h1",
                                "align": "center",
                                "title_color": "#0C0C0C",
                                "typography_typography": "custom",
                                "typography_font_family": "Josefin Sans",
                                "typography_font_size": {
                                    "unit": "em",
                                    "size": 4.444,
                                    "sizes": []
                                },
                                "typography_font_size_tablet": {
                                    "unit": "em",
                                    "size": 3.5,
                                    "sizes": []
                                },
                                "typography_font_size_mobile": {
                                    "unit": "em",
                                    "size": 2.3,
                                    "sizes": []
                                },
                                "typography_font_weight": "600",
                                "typography_text_transform": "none",
                                "typography_text_decoration": "none",
                                "typography_line_height": {
                                    "unit": "em",
                                    "size": 1,
                                    "sizes": []
                                },
                                "typography_letter_spacing": {
                                    "unit": "px",
                                    "size": 0,
                                    "sizes": []
                                },
                                "_margin": {
                                    "unit": "px",
                                    "top": "0",
                                    "right": "0",
                                    "bottom": "0",
                                    "left": "0",
                                    "isLinked": false
                                },
                                "_margin_tablet": {
                                    "unit": "px",
                                    "top": "0",
                                    "right": "0",
                                    "bottom": "0",
                                    "left": "0",
                                    "isLinked": false
                                },
                                "_margin_mobile": {
                                    "unit": "px",
                                    "top": "0",
                                    "right": "0",
                                    "bottom": "0",
                                    "left": "0",
                                    "isLinked": false
                                },
                                "_padding": {
                                    "unit": "px",
                                    "top": "0",
                                    "right": "0",
                                    "bottom": "0",
                                    "left": "0",
                                    "isLinked": false
                                },
                                "_padding_tablet": {
                                    "unit": "px",
                                    "top": "0",
                                    "right": "0",
                                    "bottom": "0",
                                    "left": "0",
                                    "isLinked": false
                                },
                                "_padding_mobile": {
                                    "unit": "px",
                                    "top": "0",
                                    "right": "0",
                                    "bottom": "0",
                                    "left": "0",
                                    "isLinked": false
                                },
                                "_animation": "zoomIn",
                                "animation_duration": "slow",
                                "_animation_delay": 500
                            },
                            "elements": [],
                            "isInner": false,
                            "widgetType": "heading",
                            "elType": "widget"
                        }
                    ],
                    "isInner": false,
                    "elType": "column"
                }
            ],
            "isInner": false,
            "elType": "section"
        }
    ]
}