{
    "version": "0.4",
    "title": "Home 3 (pro)",
    "type": "section",
    "metadata": {
        "template_type": "single-home",
        "include_in_zip": "1",
        "elementor_pro_required": "1",
        "wp_page_template": "elementor_header_footer"
    },
    "content": [
        {
            "id": "70d44e69",
            "settings": {
                "layout": "full_width",
                "margin": {
                    "unit": "px",
                    "top": "0",
                    "right": 0,
                    "bottom": "0",
                    "left": 0,
                    "isLinked": false
                },
                "padding": {
                    "unit": "px",
                    "top": "0",
                    "right": "0",
                    "bottom": "0",
                    "left": "0",
                    "isLinked": false
                },
                "background_background": "classic",
                "background_color": "#FFFFFF",
                "margin_mobile": {
                    "unit": "px",
                    "top": "0",
                    "right": 0,
                    "bottom": "0",
                    "left": 0,
                    "isLinked": false
                },
                "padding_mobile": {
                    "unit": "px",
                    "top": "0",
                    "right": "0",
                    "bottom": "0",
                    "left": "0",
                    "isLinked": false
                }
            },
            "elements": [
                {
                    "id": "7ece39f7",
                    "settings": {
                        "_column_size": 100,
                        "_inline_size": null,
                        "margin": {
                            "unit": "px",
                            "top": "0",
                            "right": "0",
                            "bottom": "0",
                            "left": "0",
                            "isLinked": false
                        },
                        "padding": {
                            "unit": "px",
                            "top": "0",
                            "right": "0",
                            "bottom": "0",
                            "left": "0",
                            "isLinked": false
                        },
                        "space_between_widgets_mobile": 0
                    },
                    "elements": [
                        {
                            "id": "56800a2f",
                            "settings": {
                                "slides": [
                                    {
                                        "heading": "Create. Dream. Discover.",
                                        "description": "Make it simple, but significant",
                                        "button_text": "",
                                        "background_color": "#833ca3",
                                        "_id": "7e496e4",
                                        "background_image": {
                                            "url": "http:\/\/template-kit.themerex.net\/creative-portfolio\/wp-content\/uploads\/sites\/2\/2020\/01\/john-weinhardt-aAnhVJwp9o0-unsplash.jpg",
                                            "id": 2680
                                        },
                                        "background_size": "cover",
                                        "background_ken_burns": "",
                                        "zoom_direction": "in",
                                        "background_overlay": "yes",
                                        "background_overlay_color": "rgba(12, 12, 12, 0.3)",
                                        "background_overlay_blend_mode": "",
                                        "link": {
                                            "url": "#",
                                            "is_external": "",
                                            "nofollow": ""
                                        },
                                        "link_click": "slide",
                                        "custom_style": "",
                                        "horizontal_position": "",
                                        "vertical_position": "",
                                        "text_align": "",
                                        "content_color": "",
                                        "repeater_text_shadow_text_shadow_type": "",
                                        "repeater_text_shadow_text_shadow": {
                                            "horizontal": 0,
                                            "vertical": 0,
                                            "blur": 10,
                                            "color": "rgba(0,0,0,0.3)"
                                        }
                                    },
                                    {
                                        "heading": "Think. Believe. Implement",
                                        "description": "Extend the boundaries of mind",
                                        "button_text": "",
                                        "background_color": "#4054b2",
                                        "_id": "37f5094",
                                        "background_image": {
                                            "url": "http:\/\/template-kit.themerex.net\/creative-portfolio\/wp-content\/uploads\/sites\/2\/2020\/01\/esther-jiao-ADv0GiMBlmI-unsplash.jpg",
                                            "id": 2709
                                        },
                                        "background_size": "cover",
                                        "background_ken_burns": "",
                                        "zoom_direction": "in",
                                        "background_overlay": "yes",
                                        "background_overlay_color": "rgba(12, 12, 12, 0.3)",
                                        "background_overlay_blend_mode": "",
                                        "link": {
                                            "url": "",
                                            "is_external": "",
                                            "nofollow": ""
                                        },
                                        "link_click": "slide",
                                        "custom_style": "",
                                        "horizontal_position": "",
                                        "vertical_position": "",
                                        "text_align": "",
                                        "content_color": "",
                                        "repeater_text_shadow_text_shadow_type": "",
                                        "repeater_text_shadow_text_shadow": {
                                            "horizontal": 0,
                                            "vertical": 0,
                                            "blur": 10,
                                            "color": "rgba(0,0,0,0.3)"
                                        }
                                    },
                                    {
                                        "heading": "The future is in your mind",
                                        "description": "Fresh ideas for perfect design",
                                        "button_text": "",
                                        "background_color": "#1abc9c",
                                        "_id": "2d13fcc",
                                        "background_image": {
                                            "url": "http:\/\/template-kit.themerex.net\/creative-portfolio\/wp-content\/uploads\/sites\/2\/2020\/01\/diana-akhmetianova-s358rpxEALI-unsplash-scaled.jpg",
                                            "id": 2707
                                        },
                                        "background_size": "cover",
                                        "background_ken_burns": "",
                                        "zoom_direction": "in",
                                        "background_overlay": "yes",
                                        "background_overlay_color": "rgba(12, 12, 12, 0.3)",
                                        "background_overlay_blend_mode": "",
                                        "link": {
                                            "url": "",
                                            "is_external": "",
                                            "nofollow": ""
                                        },
                                        "link_click": "slide",
                                        "custom_style": "",
                                        "horizontal_position": "",
                                        "vertical_position": "",
                                        "text_align": "",
                                        "content_color": "",
                                        "repeater_text_shadow_text_shadow_type": "",
                                        "repeater_text_shadow_text_shadow": {
                                            "horizontal": 0,
                                            "vertical": 0,
                                            "blur": 10,
                                            "color": "rgba(0,0,0,0.3)"
                                        }
                                    }
                                ],
                                "slides_height": {
                                    "unit": "vh",
                                    "size": 100,
                                    "sizes": []
                                },
                                "navigation": "dots",
                                "content_max_width": {
                                    "unit": "%",
                                    "size": 90,
                                    "sizes": []
                                },
                                "slides_padding": {
                                    "unit": "px",
                                    "top": "0",
                                    "right": "0",
                                    "bottom": "0",
                                    "left": "0",
                                    "isLinked": false
                                },
                                "heading_color": "#FFFFFF",
                                "heading_typography_typography": "custom",
                                "heading_typography_font_family": "Josefin Sans",
                                "heading_typography_font_size": {
                                    "unit": "em",
                                    "size": 3.889,
                                    "sizes": []
                                },
                                "heading_typography_font_weight": "700",
                                "heading_typography_text_transform": "capitalize",
                                "heading_typography_text_decoration": "none",
                                "heading_typography_line_height": {
                                    "unit": "em",
                                    "size": 1.1,
                                    "sizes": []
                                },
                                "heading_typography_letter_spacing": {
                                    "unit": "px",
                                    "size": 0,
                                    "sizes": []
                                },
                                "description_spacing": {
                                    "unit": "px",
                                    "size": 0,
                                    "sizes": []
                                },
                                "description_color": "#FFFFFF",
                                "description_typography_typography": "custom",
                                "description_typography_font_family": "Josefin Sans",
                                "description_typography_font_size": {
                                    "unit": "em",
                                    "size": 1.111,
                                    "sizes": []
                                },
                                "description_typography_font_weight": "600",
                                "description_typography_text_transform": "none",
                                "description_typography_font_style": "normal",
                                "description_typography_line_height": {
                                    "unit": "em",
                                    "size": 1,
                                    "sizes": []
                                },
                                "description_typography_letter_spacing": {
                                    "unit": "px",
                                    "size": 0,
                                    "sizes": []
                                },
                                "arrows_size": {
                                    "unit": "px",
                                    "size": 0,
                                    "sizes": []
                                },
                                "dots_size": {
                                    "unit": "px",
                                    "size": 12,
                                    "sizes": []
                                },
                                "dots_color": "#FFFFFF",
                                "_margin": {
                                    "unit": "px",
                                    "top": "0",
                                    "right": "0",
                                    "bottom": "0",
                                    "left": "0",
                                    "isLinked": false
                                },
                                "_padding": {
                                    "unit": "px",
                                    "top": "0",
                                    "right": "0",
                                    "bottom": "0",
                                    "left": "0",
                                    "isLinked": false
                                },
                                "_element_width": "inherit",
                                "_element_vertical_align": "center",
                                "slides_height_tablet": {
                                    "unit": "vh",
                                    "size": 100,
                                    "sizes": []
                                },
                                "content_max_width_tablet": {
                                    "unit": "%",
                                    "size": 100,
                                    "sizes": []
                                },
                                "slides_padding_tablet": {
                                    "unit": "px",
                                    "top": "0",
                                    "right": "0",
                                    "bottom": "0",
                                    "left": "0",
                                    "isLinked": false
                                },
                                "slides_padding_mobile": {
                                    "unit": "px",
                                    "top": "0",
                                    "right": "20",
                                    "bottom": "0",
                                    "left": "20",
                                    "isLinked": false
                                },
                                "heading_typography_font_size_mobile": {
                                    "unit": "em",
                                    "size": 3,
                                    "sizes": []
                                },
                                "_margin_mobile": {
                                    "unit": "px",
                                    "top": "0",
                                    "right": "0",
                                    "bottom": "0",
                                    "left": "0",
                                    "isLinked": false
                                },
                                "_padding_mobile": {
                                    "unit": "px",
                                    "top": "0",
                                    "right": "0",
                                    "bottom": "0",
                                    "left": "0",
                                    "isLinked": false
                                },
                                "heading_typography_font_size_tablet": {
                                    "unit": "em",
                                    "size": 3.2,
                                    "sizes": []
                                },
                                "autoplay": "",
                                "_margin_tablet": {
                                    "unit": "px",
                                    "top": "0",
                                    "right": "0",
                                    "bottom": "0",
                                    "left": "0",
                                    "isLinked": false
                                },
                                "_padding_tablet": {
                                    "unit": "px",
                                    "top": "0",
                                    "right": "0",
                                    "bottom": "0",
                                    "left": "0",
                                    "isLinked": false
                                }
                            },
                            "elements": [],
                            "isInner": false,
                            "widgetType": "slides",
                            "elType": "widget"
                        }
                    ],
                    "isInner": false,
                    "elType": "column"
                }
            ],
            "isInner": false,
            "elType": "section"
        },
        {
            "id": "43e0d25d",
            "settings": {
                "content_width": {
                    "unit": "px",
                    "size": 970,
                    "sizes": []
                },
                "gap": "no",
                "background_background": "classic",
                "background_color": "#FFFFFF",
                "margin": {
                    "unit": "px",
                    "top": "0",
                    "right": 0,
                    "bottom": "0",
                    "left": 0,
                    "isLinked": false
                },
                "padding": {
                    "unit": "px",
                    "top": "160",
                    "right": "0",
                    "bottom": "0",
                    "left": "0",
                    "isLinked": false
                },
                "margin_tablet": {
                    "unit": "px",
                    "top": "0",
                    "right": 0,
                    "bottom": "0",
                    "left": 0,
                    "isLinked": false
                },
                "padding_tablet": {
                    "unit": "px",
                    "top": "100",
                    "right": "30",
                    "bottom": "0",
                    "left": "30",
                    "isLinked": false
                },
                "margin_mobile": {
                    "unit": "px",
                    "top": "0",
                    "right": 0,
                    "bottom": "0",
                    "left": 0,
                    "isLinked": false
                },
                "padding_mobile": {
                    "unit": "px",
                    "top": "60",
                    "right": "20",
                    "bottom": "0",
                    "left": "20",
                    "isLinked": false
                }
            },
            "elements": [
                {
                    "id": "41ef7bfc",
                    "settings": {
                        "_column_size": 100,
                        "_inline_size": null,
                        "space_between_widgets": 0,
                        "margin": {
                            "unit": "px",
                            "top": "0",
                            "right": "0",
                            "bottom": "0",
                            "left": "0",
                            "isLinked": false
                        },
                        "padding": {
                            "unit": "px",
                            "top": "0",
                            "right": "0",
                            "bottom": "0",
                            "left": "0",
                            "isLinked": false
                        },
                        "space_between_widgets_mobile": 0,
                        "margin_mobile": {
                            "unit": "px",
                            "top": "0",
                            "right": "0",
                            "bottom": "0",
                            "left": "0",
                            "isLinked": false
                        },
                        "padding_mobile": {
                            "unit": "px",
                            "top": "0",
                            "right": "0",
                            "bottom": "0",
                            "left": "0",
                            "isLinked": false
                        },
                        "space_between_widgets_tablet": 0
                    },
                    "elements": [
                        {
                            "id": "38b642",
                            "settings": {
                                "title": "Testimonial",
                                "header_size": "h3",
                                "align": "center",
                                "title_color": "#0C0C0C",
                                "typography_typography": "custom",
                                "typography_font_family": "Josefin Sans",
                                "typography_font_size": {
                                    "unit": "em",
                                    "size": 1.111,
                                    "sizes": []
                                },
                                "typography_font_weight": "600",
                                "typography_text_transform": "capitalize",
                                "typography_font_style": "normal",
                                "typography_text_decoration": "none",
                                "typography_line_height": {
                                    "unit": "em",
                                    "size": 1,
                                    "sizes": []
                                },
                                "typography_letter_spacing": {
                                    "unit": "px",
                                    "size": 0,
                                    "sizes": []
                                },
                                "_margin": {
                                    "unit": "px",
                                    "top": "0",
                                    "right": "0",
                                    "bottom": "0",
                                    "left": "0",
                                    "isLinked": false
                                },
                                "_padding": {
                                    "unit": "px",
                                    "top": "0",
                                    "right": "0",
                                    "bottom": "0",
                                    "left": "0",
                                    "isLinked": false
                                },
                                "_animation": "fadeInUp",
                                "_margin_mobile": {
                                    "unit": "px",
                                    "top": "0",
                                    "right": "0",
                                    "bottom": "0",
                                    "left": "0",
                                    "isLinked": false
                                },
                                "_padding_mobile": {
                                    "unit": "px",
                                    "top": "0",
                                    "right": "0",
                                    "bottom": "0",
                                    "left": "0",
                                    "isLinked": false
                                },
                                "_animation_mobile": "fadeIn",
                                "typography_font_size_tablet": {
                                    "unit": "em",
                                    "size": "",
                                    "sizes": []
                                },
                                "typography_font_size_mobile": {
                                    "unit": "em",
                                    "size": 1,
                                    "sizes": []
                                }
                            },
                            "elements": [],
                            "isInner": false,
                            "widgetType": "heading",
                            "elType": "widget"
                        },
                        {
                            "id": "7e6ca9b7",
                            "settings": {
                                "title": "What I like about photographs is that they capture a moment that\u2019s gone forever, impossible to reproduce",
                                "align": "center",
                                "title_color": "#0C0C0C",
                                "typography_typography": "custom",
                                "typography_font_family": "Josefin Sans",
                                "typography_font_size": {
                                    "unit": "em",
                                    "size": 2.778,
                                    "sizes": []
                                },
                                "typography_font_weight": "600",
                                "typography_text_transform": "none",
                                "typography_font_style": "normal",
                                "typography_text_decoration": "none",
                                "typography_line_height": {
                                    "unit": "em",
                                    "size": 1.2,
                                    "sizes": []
                                },
                                "typography_letter_spacing": {
                                    "unit": "px",
                                    "size": 0,
                                    "sizes": []
                                },
                                "_margin": {
                                    "unit": "px",
                                    "top": "41",
                                    "right": "0",
                                    "bottom": "0",
                                    "left": "0",
                                    "isLinked": false
                                },
                                "_padding": {
                                    "unit": "px",
                                    "top": "0",
                                    "right": "0",
                                    "bottom": "0",
                                    "left": "0",
                                    "isLinked": false
                                },
                                "_margin_tablet": {
                                    "unit": "px",
                                    "top": "22",
                                    "right": "0",
                                    "bottom": "0",
                                    "left": "0",
                                    "isLinked": false
                                },
                                "_padding_tablet": {
                                    "unit": "px",
                                    "top": "0",
                                    "right": "0",
                                    "bottom": "0",
                                    "left": "0",
                                    "isLinked": false
                                },
                                "_animation": "fadeInUp",
                                "_animation_delay": 100,
                                "typography_font_size_mobile": {
                                    "unit": "em",
                                    "size": 1.9,
                                    "sizes": []
                                },
                                "_margin_mobile": {
                                    "unit": "px",
                                    "top": "15",
                                    "right": "0",
                                    "bottom": "0",
                                    "left": "0",
                                    "isLinked": false
                                },
                                "_padding_mobile": {
                                    "unit": "px",
                                    "top": "0",
                                    "right": "0",
                                    "bottom": "0",
                                    "left": "0",
                                    "isLinked": false
                                },
                                "_animation_mobile": "fadeIn",
                                "typography_font_size_tablet": {
                                    "unit": "em",
                                    "size": 2.4,
                                    "sizes": []
                                },
                                "typography_line_height_mobile": {
                                    "unit": "em",
                                    "size": 1.1,
                                    "sizes": []
                                },
                                "typography_letter_spacing_mobile": {
                                    "unit": "px",
                                    "size": 0,
                                    "sizes": []
                                }
                            },
                            "elements": [],
                            "isInner": false,
                            "widgetType": "heading",
                            "elType": "widget"
                        },
                        {
                            "id": "6c98a522",
                            "settings": {
                                "text": "Portfolio",
                                "align": "center",
                                "typography_typography": "custom",
                                "typography_font_family": "Josefin Sans",
                                "typography_font_size": {
                                    "unit": "em",
                                    "size": 1,
                                    "sizes": []
                                },
                                "typography_font_weight": "600",
                                "typography_text_transform": "capitalize",
                                "typography_font_style": "normal",
                                "typography_text_decoration": "none",
                                "typography_line_height": {
                                    "unit": "em",
                                    "size": 1,
                                    "sizes": []
                                },
                                "typography_letter_spacing": {
                                    "unit": "px",
                                    "size": 0,
                                    "sizes": []
                                },
                                "button_text_color": "#E93314",
                                "background_color": "rgba(1, 1, 1, 0)",
                                "hover_color": "#E93314",
                                "button_background_hover_color": "rgba(1, 1, 1, 0)",
                                "hover_animation": "pop",
                                "border_radius": {
                                    "unit": "px",
                                    "top": "0",
                                    "right": "0",
                                    "bottom": "0",
                                    "left": "0",
                                    "isLinked": false
                                },
                                "text_padding": {
                                    "unit": "px",
                                    "top": "0",
                                    "right": "0",
                                    "bottom": "0",
                                    "left": "0",
                                    "isLinked": false
                                },
                                "_margin": {
                                    "unit": "px",
                                    "top": "47",
                                    "right": "0",
                                    "bottom": "0",
                                    "left": "0",
                                    "isLinked": false
                                },
                                "_padding": {
                                    "unit": "px",
                                    "top": "0",
                                    "right": "0",
                                    "bottom": "0",
                                    "left": "0",
                                    "isLinked": false
                                },
                                "_margin_tablet": {
                                    "unit": "px",
                                    "top": "20",
                                    "right": "0",
                                    "bottom": "0",
                                    "left": "0",
                                    "isLinked": false
                                },
                                "_padding_tablet": {
                                    "unit": "px",
                                    "top": "0",
                                    "right": "0",
                                    "bottom": "0",
                                    "left": "0",
                                    "isLinked": false
                                },
                                "_animation": "fadeInUp",
                                "_animation_delay": 200,
                                "text_padding_tablet": {
                                    "unit": "px",
                                    "top": "0",
                                    "right": "0",
                                    "bottom": "0",
                                    "left": "0",
                                    "isLinked": false
                                },
                                "text_padding_mobile": {
                                    "unit": "px",
                                    "top": "0",
                                    "right": "0",
                                    "bottom": "0",
                                    "left": "0",
                                    "isLinked": false
                                },
                                "_margin_mobile": {
                                    "unit": "px",
                                    "top": "7",
                                    "right": "0",
                                    "bottom": "0",
                                    "left": "0",
                                    "isLinked": false
                                },
                                "_padding_mobile": {
                                    "unit": "px",
                                    "top": "0",
                                    "right": "0",
                                    "bottom": "0",
                                    "left": "0",
                                    "isLinked": false
                                },
                                "_animation_mobile": "fadeIn"
                            },
                            "elements": [],
                            "isInner": false,
                            "widgetType": "button",
                            "elType": "widget"
                        }
                    ],
                    "isInner": false,
                    "elType": "column"
                }
            ],
            "isInner": false,
            "elType": "section"
        },
        {
            "id": "21936f9c",
            "settings": {
                "content_width": {
                    "unit": "px",
                    "size": 1170,
                    "sizes": []
                },
                "gap": "no",
                "content_position": "top",
                "overflow": "hidden",
                "html_tag": "section",
                "structure": "30",
                "background_background": "classic",
                "background_color": "#FFFFFF",
                "margin": {
                    "unit": "px",
                    "top": "0",
                    "right": 0,
                    "bottom": "0",
                    "left": 0,
                    "isLinked": false
                },
                "padding": {
                    "unit": "px",
                    "top": "154",
                    "right": "0",
                    "bottom": "0",
                    "left": "0",
                    "isLinked": false
                },
                "margin_tablet": {
                    "unit": "px",
                    "top": "0",
                    "right": 0,
                    "bottom": "0",
                    "left": 0,
                    "isLinked": false
                },
                "padding_tablet": {
                    "unit": "px",
                    "top": "95",
                    "right": "30",
                    "bottom": "0",
                    "left": "30",
                    "isLinked": false
                },
                "margin_mobile": {
                    "unit": "px",
                    "top": "0",
                    "right": 0,
                    "bottom": "0",
                    "left": 0,
                    "isLinked": false
                },
                "padding_mobile": {
                    "unit": "px",
                    "top": "55",
                    "right": "20",
                    "bottom": "0",
                    "left": "20",
                    "isLinked": false
                }
            },
            "elements": [
                {
                    "id": "7a497ff2",
                    "settings": {
                        "_column_size": 33,
                        "_inline_size": null,
                        "space_between_widgets": 30,
                        "margin": {
                            "unit": "px",
                            "top": "0",
                            "right": "20",
                            "bottom": "0",
                            "left": "0",
                            "isLinked": false
                        },
                        "padding": {
                            "unit": "px",
                            "top": "0",
                            "right": "0",
                            "bottom": "0",
                            "left": "0",
                            "isLinked": false
                        },
                        "space_between_widgets_tablet": 30,
                        "margin_tablet": {
                            "unit": "px",
                            "top": "0",
                            "right": "20",
                            "bottom": "0",
                            "left": "0",
                            "isLinked": false
                        },
                        "padding_tablet": {
                            "unit": "px",
                            "top": "0",
                            "right": "0",
                            "bottom": "0",
                            "left": "0",
                            "isLinked": false
                        },
                        "space_between_widgets_mobile": 20,
                        "margin_mobile": {
                            "unit": "px",
                            "top": "0",
                            "right": "0",
                            "bottom": "0",
                            "left": "0",
                            "isLinked": false
                        },
                        "padding_mobile": {
                            "unit": "px",
                            "top": "0",
                            "right": "0",
                            "bottom": "0",
                            "left": "0",
                            "isLinked": false
                        }
                    },
                    "elements": [
                        {
                            "id": "2b21ad42",
                            "settings": {
                                "image": {
                                    "url": "http:\/\/template-kit.themerex.net\/creative-portfolio\/wp-content\/uploads\/sites\/2\/2020\/01\/ruslan-bardash-FnfMtI8w6-E-unsplash-scaled.jpg",
                                    "id": 2690
                                },
                                "image_size": "custom",
                                "image_custom_dimension": {
                                    "width": "370",
                                    "height": "484"
                                },
                                "width": {
                                    "unit": "%",
                                    "size": 100,
                                    "sizes": []
                                },
                                "css_filters_css_filter": "custom",
                                "image_border_radius": {
                                    "unit": "px",
                                    "top": "8",
                                    "right": "8",
                                    "bottom": "8",
                                    "left": "8",
                                    "isLinked": true
                                },
                                "_margin": {
                                    "unit": "px",
                                    "top": "0",
                                    "right": "0",
                                    "bottom": "0",
                                    "left": "0",
                                    "isLinked": false
                                },
                                "_padding": {
                                    "unit": "px",
                                    "top": "0",
                                    "right": "0",
                                    "bottom": "0",
                                    "left": "0",
                                    "isLinked": false
                                },
                                "_margin_tablet": {
                                    "unit": "px",
                                    "top": "0",
                                    "right": "0",
                                    "bottom": "0",
                                    "left": "0",
                                    "isLinked": false
                                },
                                "_padding_tablet": {
                                    "unit": "px",
                                    "top": "0",
                                    "right": "0",
                                    "bottom": "0",
                                    "left": "0",
                                    "isLinked": false
                                },
                                "_animation": "fadeIn",
                                "_margin_mobile": {
                                    "unit": "px",
                                    "top": "0",
                                    "right": "0",
                                    "bottom": "0",
                                    "left": "0",
                                    "isLinked": false
                                },
                                "_padding_mobile": {
                                    "unit": "px",
                                    "top": "0",
                                    "right": "0",
                                    "bottom": "0",
                                    "left": "0",
                                    "isLinked": false
                                },
                                "hover_animation": "float",
                                "_animation_mobile": "fadeIn",
                                "link_to": "file",
                                "open_lightbox": "yes"
                            },
                            "elements": [],
                            "isInner": false,
                            "widgetType": "image",
                            "elType": "widget"
                        },
                        {
                            "id": "78426d5a",
                            "settings": {
                                "image": {
                                    "url": "http:\/\/template-kit.themerex.net\/creative-portfolio\/wp-content\/uploads\/sites\/2\/2020\/01\/bartosz-sujkowski-WP7HGnkmz_E-unsplash.jpg",
                                    "id": 2705
                                },
                                "image_size": "custom",
                                "image_custom_dimension": {
                                    "width": "370",
                                    "height": "290"
                                },
                                "width": {
                                    "unit": "%",
                                    "size": 100,
                                    "sizes": []
                                },
                                "image_border_radius": {
                                    "unit": "px",
                                    "top": "8",
                                    "right": "8",
                                    "bottom": "8",
                                    "left": "8",
                                    "isLinked": true
                                },
                                "_margin": {
                                    "unit": "px",
                                    "top": "0",
                                    "right": "0",
                                    "bottom": "0",
                                    "left": "0",
                                    "isLinked": false
                                },
                                "_padding": {
                                    "unit": "px",
                                    "top": "0",
                                    "right": "0",
                                    "bottom": "0",
                                    "left": "0",
                                    "isLinked": false
                                },
                                "_margin_tablet": {
                                    "unit": "px",
                                    "top": "0",
                                    "right": "0",
                                    "bottom": "0",
                                    "left": "0",
                                    "isLinked": false
                                },
                                "_padding_tablet": {
                                    "unit": "px",
                                    "top": "0",
                                    "right": "0",
                                    "bottom": "0",
                                    "left": "0",
                                    "isLinked": false
                                },
                                "_animation": "fadeIn",
                                "_margin_mobile": {
                                    "unit": "px",
                                    "top": "0",
                                    "right": "0",
                                    "bottom": "0",
                                    "left": "0",
                                    "isLinked": false
                                },
                                "_padding_mobile": {
                                    "unit": "px",
                                    "top": "0",
                                    "right": "0",
                                    "bottom": "0",
                                    "left": "0",
                                    "isLinked": false
                                },
                                "hover_animation": "float",
                                "_animation_mobile": "fadeIn",
                                "link_to": "file",
                                "open_lightbox": "yes"
                            },
                            "elements": [],
                            "isInner": false,
                            "widgetType": "image",
                            "elType": "widget"
                        },
                        {
                            "id": "18dbca66",
                            "settings": {
                                "image": {
                                    "url": "http:\/\/template-kit.themerex.net\/creative-portfolio\/wp-content\/uploads\/sites\/2\/2020\/01\/matthew-hamilton-BeeMMFF_jso-unsplash-scaled.jpg",
                                    "id": 2685
                                },
                                "image_size": "custom",
                                "image_custom_dimension": {
                                    "width": "370",
                                    "height": "312"
                                },
                                "width": {
                                    "unit": "%",
                                    "size": 100,
                                    "sizes": []
                                },
                                "image_border_radius": {
                                    "unit": "px",
                                    "top": "8",
                                    "right": "8",
                                    "bottom": "8",
                                    "left": "8",
                                    "isLinked": true
                                },
                                "_margin": {
                                    "unit": "px",
                                    "top": "0",
                                    "right": "0",
                                    "bottom": "0",
                                    "left": "0",
                                    "isLinked": false
                                },
                                "_padding": {
                                    "unit": "px",
                                    "top": "0",
                                    "right": "0",
                                    "bottom": "0",
                                    "left": "0",
                                    "isLinked": false
                                },
                                "_margin_tablet": {
                                    "unit": "px",
                                    "top": "0",
                                    "right": "0",
                                    "bottom": "0",
                                    "left": "0",
                                    "isLinked": false
                                },
                                "_padding_tablet": {
                                    "unit": "px",
                                    "top": "0",
                                    "right": "0",
                                    "bottom": "0",
                                    "left": "0",
                                    "isLinked": false
                                },
                                "_animation": "fadeIn",
                                "hover_animation": "float",
                                "_animation_mobile": "fadeIn",
                                "link_to": "file",
                                "open_lightbox": "yes"
                            },
                            "elements": [],
                            "isInner": false,
                            "widgetType": "image",
                            "elType": "widget"
                        }
                    ],
                    "isInner": false,
                    "elType": "column"
                },
                {
                    "id": "89b8f9e",
                    "settings": {
                        "_column_size": 33,
                        "_inline_size": null,
                        "space_between_widgets": 30,
                        "margin": {
                            "unit": "px",
                            "top": "0",
                            "right": "10",
                            "bottom": "0",
                            "left": "10",
                            "isLinked": false
                        },
                        "padding": {
                            "unit": "px",
                            "top": "0",
                            "right": "0",
                            "bottom": "0",
                            "left": "0",
                            "isLinked": false
                        },
                        "space_between_widgets_tablet": 30,
                        "margin_tablet": {
                            "unit": "px",
                            "top": "0",
                            "right": "10",
                            "bottom": "0",
                            "left": "10",
                            "isLinked": false
                        },
                        "padding_tablet": {
                            "unit": "px",
                            "top": "0",
                            "right": "0",
                            "bottom": "0",
                            "left": "0",
                            "isLinked": false
                        },
                        "space_between_widgets_mobile": 20,
                        "margin_mobile": {
                            "unit": "px",
                            "top": "20",
                            "right": "0",
                            "bottom": "0",
                            "left": "0",
                            "isLinked": false
                        },
                        "padding_mobile": {
                            "unit": "px",
                            "top": "0",
                            "right": "0",
                            "bottom": "0",
                            "left": "0",
                            "isLinked": false
                        }
                    },
                    "elements": [
                        {
                            "id": "7d151a25",
                            "settings": {
                                "image": {
                                    "url": "http:\/\/template-kit.themerex.net\/creative-portfolio\/wp-content\/uploads\/sites\/2\/2020\/01\/apostolos-vamvouras-mKi4QEJXRCs-unsplash-scaled.jpg",
                                    "id": 2703
                                },
                                "image_size": "custom",
                                "image_custom_dimension": {
                                    "width": "370",
                                    "height": "359"
                                },
                                "width": {
                                    "unit": "%",
                                    "size": 100,
                                    "sizes": []
                                },
                                "image_border_radius": {
                                    "unit": "px",
                                    "top": "8",
                                    "right": "8",
                                    "bottom": "8",
                                    "left": "8",
                                    "isLinked": true
                                },
                                "_margin": {
                                    "unit": "px",
                                    "top": "0",
                                    "right": "0",
                                    "bottom": "0",
                                    "left": "0",
                                    "isLinked": false
                                },
                                "_padding": {
                                    "unit": "px",
                                    "top": "0",
                                    "right": "0",
                                    "bottom": "0",
                                    "left": "0",
                                    "isLinked": false
                                },
                                "_margin_tablet": {
                                    "unit": "px",
                                    "top": "0",
                                    "right": "0",
                                    "bottom": "0",
                                    "left": "0",
                                    "isLinked": false
                                },
                                "_padding_tablet": {
                                    "unit": "px",
                                    "top": "0",
                                    "right": "0",
                                    "bottom": "0",
                                    "left": "0",
                                    "isLinked": false
                                },
                                "_animation": "fadeIn",
                                "_margin_mobile": {
                                    "unit": "px",
                                    "top": "0",
                                    "right": "0",
                                    "bottom": "0",
                                    "left": "0",
                                    "isLinked": false
                                },
                                "_padding_mobile": {
                                    "unit": "px",
                                    "top": "0",
                                    "right": "0",
                                    "bottom": "0",
                                    "left": "0",
                                    "isLinked": false
                                },
                                "hover_animation": "float",
                                "_animation_mobile": "fadeIn",
                                "link_to": "file",
                                "open_lightbox": "yes"
                            },
                            "elements": [],
                            "isInner": false,
                            "widgetType": "image",
                            "elType": "widget"
                        },
                        {
                            "id": "228eaadb",
                            "settings": {
                                "image": {
                                    "url": "http:\/\/template-kit.themerex.net\/creative-portfolio\/wp-content\/uploads\/sites\/2\/2020\/01\/esther-jiao-ADv0GiMBlmI-unsplash.jpg",
                                    "id": 2709
                                },
                                "image_size": "custom",
                                "image_custom_dimension": {
                                    "width": "370",
                                    "height": "290"
                                },
                                "width": {
                                    "unit": "%",
                                    "size": 100,
                                    "sizes": []
                                },
                                "image_border_radius": {
                                    "unit": "px",
                                    "top": "8",
                                    "right": "8",
                                    "bottom": "8",
                                    "left": "8",
                                    "isLinked": true
                                },
                                "_margin": {
                                    "unit": "px",
                                    "top": "0",
                                    "right": "0",
                                    "bottom": "0",
                                    "left": "0",
                                    "isLinked": false
                                },
                                "_padding": {
                                    "unit": "px",
                                    "top": "0",
                                    "right": "0",
                                    "bottom": "0",
                                    "left": "0",
                                    "isLinked": false
                                },
                                "_margin_tablet": {
                                    "unit": "px",
                                    "top": "0",
                                    "right": "0",
                                    "bottom": "0",
                                    "left": "0",
                                    "isLinked": false
                                },
                                "_padding_tablet": {
                                    "unit": "px",
                                    "top": "0",
                                    "right": "0",
                                    "bottom": "0",
                                    "left": "0",
                                    "isLinked": false
                                },
                                "_animation": "fadeIn",
                                "_margin_mobile": {
                                    "unit": "px",
                                    "top": "0",
                                    "right": "0",
                                    "bottom": "0",
                                    "left": "0",
                                    "isLinked": false
                                },
                                "_padding_mobile": {
                                    "unit": "px",
                                    "top": "0",
                                    "right": "0",
                                    "bottom": "0",
                                    "left": "0",
                                    "isLinked": false
                                },
                                "hover_animation": "float",
                                "_animation_mobile": "fadeIn",
                                "link_to": "file",
                                "open_lightbox": "yes"
                            },
                            "elements": [],
                            "isInner": false,
                            "widgetType": "image",
                            "elType": "widget"
                        },
                        {
                            "id": "38ddcd04",
                            "settings": {
                                "image": {
                                    "url": "http:\/\/template-kit.themerex.net\/creative-portfolio\/wp-content\/uploads\/sites\/2\/2020\/01\/ruslan-bardash-4kTbAMRAHtQ-unsplash-scaled.jpg",
                                    "id": 2689
                                },
                                "image_size": "custom",
                                "image_custom_dimension": {
                                    "width": "370",
                                    "height": "469"
                                },
                                "width": {
                                    "unit": "%",
                                    "size": 100,
                                    "sizes": []
                                },
                                "image_border_radius": {
                                    "unit": "px",
                                    "top": "8",
                                    "right": "8",
                                    "bottom": "8",
                                    "left": "8",
                                    "isLinked": true
                                },
                                "_margin": {
                                    "unit": "px",
                                    "top": "0",
                                    "right": "0",
                                    "bottom": "0",
                                    "left": "0",
                                    "isLinked": false
                                },
                                "_padding": {
                                    "unit": "px",
                                    "top": "0",
                                    "right": "0",
                                    "bottom": "0",
                                    "left": "0",
                                    "isLinked": false
                                },
                                "_margin_tablet": {
                                    "unit": "px",
                                    "top": "0",
                                    "right": "0",
                                    "bottom": "0",
                                    "left": "0",
                                    "isLinked": false
                                },
                                "_padding_tablet": {
                                    "unit": "px",
                                    "top": "0",
                                    "right": "0",
                                    "bottom": "0",
                                    "left": "0",
                                    "isLinked": false
                                },
                                "_animation": "fadeIn",
                                "_margin_mobile": {
                                    "unit": "px",
                                    "top": "0",
                                    "right": "0",
                                    "bottom": "0",
                                    "left": "0",
                                    "isLinked": false
                                },
                                "_padding_mobile": {
                                    "unit": "px",
                                    "top": "0",
                                    "right": "0",
                                    "bottom": "0",
                                    "left": "0",
                                    "isLinked": false
                                },
                                "hover_animation": "float",
                                "_animation_mobile": "fadeIn",
                                "link_to": "file",
                                "open_lightbox": "yes"
                            },
                            "elements": [],
                            "isInner": false,
                            "widgetType": "image",
                            "elType": "widget"
                        }
                    ],
                    "isInner": false,
                    "elType": "column"
                },
                {
                    "id": "37bbb3f0",
                    "settings": {
                        "_column_size": 33,
                        "_inline_size": null,
                        "space_between_widgets": 30,
                        "margin": {
                            "unit": "px",
                            "top": "0",
                            "right": "0",
                            "bottom": "0",
                            "left": "20",
                            "isLinked": false
                        },
                        "padding": {
                            "unit": "px",
                            "top": "0",
                            "right": "0",
                            "bottom": "0",
                            "left": "0",
                            "isLinked": false
                        },
                        "space_between_widgets_tablet": 30,
                        "margin_tablet": {
                            "unit": "px",
                            "top": "0",
                            "right": "0",
                            "bottom": "0",
                            "left": "20",
                            "isLinked": false
                        },
                        "padding_tablet": {
                            "unit": "px",
                            "top": "0",
                            "right": "0",
                            "bottom": "0",
                            "left": "0",
                            "isLinked": false
                        },
                        "space_between_widgets_mobile": 20,
                        "margin_mobile": {
                            "unit": "px",
                            "top": "20",
                            "right": "0",
                            "bottom": "0",
                            "left": "0",
                            "isLinked": false
                        },
                        "padding_mobile": {
                            "unit": "px",
                            "top": "0",
                            "right": "0",
                            "bottom": "0",
                            "left": "0",
                            "isLinked": false
                        }
                    },
                    "elements": [
                        {
                            "id": "59956b75",
                            "settings": {
                                "image": {
                                    "url": "http:\/\/template-kit.themerex.net\/creative-portfolio\/wp-content\/uploads\/sites\/2\/2020\/01\/mae-mu-ECjY3Ypyl5g-unsplash.jpg",
                                    "id": 2684
                                },
                                "image_size": "custom",
                                "width": {
                                    "unit": "%",
                                    "size": 100,
                                    "sizes": []
                                },
                                "image_border_radius": {
                                    "unit": "px",
                                    "top": "8",
                                    "right": "8",
                                    "bottom": "8",
                                    "left": "8",
                                    "isLinked": true
                                },
                                "_margin": {
                                    "unit": "px",
                                    "top": "0",
                                    "right": "0",
                                    "bottom": "0",
                                    "left": "0",
                                    "isLinked": false
                                },
                                "_padding": {
                                    "unit": "px",
                                    "top": "0",
                                    "right": "0",
                                    "bottom": "0",
                                    "left": "0",
                                    "isLinked": false
                                },
                                "_margin_tablet": {
                                    "unit": "px",
                                    "top": "0",
                                    "right": "0",
                                    "bottom": "0",
                                    "left": "0",
                                    "isLinked": false
                                },
                                "_padding_tablet": {
                                    "unit": "px",
                                    "top": "0",
                                    "right": "0",
                                    "bottom": "0",
                                    "left": "0",
                                    "isLinked": false
                                },
                                "_animation": "fadeIn",
                                "_margin_mobile": {
                                    "unit": "px",
                                    "top": "0",
                                    "right": "0",
                                    "bottom": "0",
                                    "left": "0",
                                    "isLinked": false
                                },
                                "_padding_mobile": {
                                    "unit": "px",
                                    "top": "0",
                                    "right": "0",
                                    "bottom": "0",
                                    "left": "0",
                                    "isLinked": false
                                },
                                "hover_animation": "float",
                                "_animation_mobile": "fadeIn",
                                "link_to": "file",
                                "open_lightbox": "yes",
                                "image_custom_dimension": {
                                    "width": "370",
                                    "height": "469"
                                }
                            },
                            "elements": [],
                            "isInner": false,
                            "widgetType": "image",
                            "elType": "widget"
                        },
                        {
                            "id": "12d014c3",
                            "settings": {
                                "image": {
                                    "url": "http:\/\/template-kit.themerex.net\/creative-portfolio\/wp-content\/uploads\/sites\/2\/2020\/01\/alexander-andrews-zw07kVDaHPw-unsplash.jpg",
                                    "id": 2699
                                },
                                "image_size": "custom",
                                "image_custom_dimension": {
                                    "width": "370",
                                    "height": "312"
                                },
                                "width": {
                                    "unit": "%",
                                    "size": 100,
                                    "sizes": []
                                },
                                "image_border_radius": {
                                    "unit": "px",
                                    "top": "8",
                                    "right": "8",
                                    "bottom": "8",
                                    "left": "8",
                                    "isLinked": true
                                },
                                "_margin": {
                                    "unit": "px",
                                    "top": "0",
                                    "right": "0",
                                    "bottom": "0",
                                    "left": "0",
                                    "isLinked": false
                                },
                                "_padding": {
                                    "unit": "px",
                                    "top": "0",
                                    "right": "0",
                                    "bottom": "0",
                                    "left": "0",
                                    "isLinked": false
                                },
                                "_margin_tablet": {
                                    "unit": "px",
                                    "top": "0",
                                    "right": "0",
                                    "bottom": "0",
                                    "left": "0",
                                    "isLinked": false
                                },
                                "_padding_tablet": {
                                    "unit": "px",
                                    "top": "0",
                                    "right": "0",
                                    "bottom": "0",
                                    "left": "0",
                                    "isLinked": false
                                },
                                "_animation": "fadeIn",
                                "_margin_mobile": {
                                    "unit": "px",
                                    "top": "0",
                                    "right": "0",
                                    "bottom": "0",
                                    "left": "0",
                                    "isLinked": false
                                },
                                "_padding_mobile": {
                                    "unit": "px",
                                    "top": "0",
                                    "right": "0",
                                    "bottom": "0",
                                    "left": "0",
                                    "isLinked": false
                                },
                                "hover_animation": "float",
                                "_animation_mobile": "fadeIn",
                                "link_to": "file",
                                "open_lightbox": "yes"
                            },
                            "elements": [],
                            "isInner": false,
                            "widgetType": "image",
                            "elType": "widget"
                        },
                        {
                            "id": "305b7fe9",
                            "settings": {
                                "image": {
                                    "url": "http:\/\/template-kit.themerex.net\/creative-portfolio\/wp-content\/uploads\/sites\/2\/2020\/01\/viktor-talashuk-Sjk38bu7VXg-unsplash.jpg",
                                    "id": 2696
                                },
                                "image_size": "custom",
                                "image_custom_dimension": {
                                    "width": "370",
                                    "height": "290"
                                },
                                "width": {
                                    "unit": "%",
                                    "size": 100,
                                    "sizes": []
                                },
                                "image_border_radius": {
                                    "unit": "px",
                                    "top": "8",
                                    "right": "8",
                                    "bottom": "8",
                                    "left": "8",
                                    "isLinked": true
                                },
                                "_margin": {
                                    "unit": "px",
                                    "top": "0",
                                    "right": "0",
                                    "bottom": "0",
                                    "left": "0",
                                    "isLinked": false
                                },
                                "_padding": {
                                    "unit": "px",
                                    "top": "0",
                                    "right": "0",
                                    "bottom": "0",
                                    "left": "0",
                                    "isLinked": false
                                },
                                "_margin_tablet": {
                                    "unit": "px",
                                    "top": "0",
                                    "right": "0",
                                    "bottom": "0",
                                    "left": "0",
                                    "isLinked": false
                                },
                                "_padding_tablet": {
                                    "unit": "px",
                                    "top": "0",
                                    "right": "0",
                                    "bottom": "0",
                                    "left": "0",
                                    "isLinked": false
                                },
                                "_animation": "fadeIn",
                                "_margin_mobile": {
                                    "unit": "px",
                                    "top": "0",
                                    "right": "0",
                                    "bottom": "0",
                                    "left": "0",
                                    "isLinked": false
                                },
                                "_padding_mobile": {
                                    "unit": "px",
                                    "top": "0",
                                    "right": "0",
                                    "bottom": "0",
                                    "left": "0",
                                    "isLinked": false
                                },
                                "hover_animation": "float",
                                "_animation_mobile": "fadeIn",
                                "link_to": "file",
                                "open_lightbox": "yes"
                            },
                            "elements": [],
                            "isInner": false,
                            "widgetType": "image",
                            "elType": "widget"
                        }
                    ],
                    "isInner": false,
                    "elType": "column"
                }
            ],
            "isInner": false,
            "elType": "section"
        },
        {
            "id": "5c8a0b5",
            "settings": {
                "background_background": "classic",
                "background_color": "#FFFFFF",
                "margin": {
                    "unit": "px",
                    "top": "0",
                    "right": 0,
                    "bottom": "0",
                    "left": 0,
                    "isLinked": false
                },
                "padding": {
                    "unit": "px",
                    "top": "71",
                    "right": "0",
                    "bottom": "160",
                    "left": "0",
                    "isLinked": false
                },
                "margin_tablet": {
                    "unit": "px",
                    "top": "0",
                    "right": 0,
                    "bottom": "0",
                    "left": 0,
                    "isLinked": false
                },
                "margin_mobile": {
                    "unit": "px",
                    "top": "0",
                    "right": 0,
                    "bottom": "0",
                    "left": 0,
                    "isLinked": false
                },
                "padding_tablet": {
                    "unit": "px",
                    "top": "60",
                    "right": "0",
                    "bottom": "100",
                    "left": "0",
                    "isLinked": false
                },
                "padding_mobile": {
                    "unit": "px",
                    "top": "20",
                    "right": "0",
                    "bottom": "59",
                    "left": "0",
                    "isLinked": false
                }
            },
            "elements": [
                {
                    "id": "921f643",
                    "settings": {
                        "_column_size": 100,
                        "_inline_size": null,
                        "margin": {
                            "unit": "px",
                            "top": "0",
                            "right": "0",
                            "bottom": "0",
                            "left": "0",
                            "isLinked": false
                        },
                        "padding": {
                            "unit": "px",
                            "top": "0",
                            "right": "0",
                            "bottom": "0",
                            "left": "0",
                            "isLinked": false
                        }
                    },
                    "elements": [
                        {
                            "id": "477145fc",
                            "settings": {
                                "text": "View  More",
                                "align": "center",
                                "typography_typography": "custom",
                                "typography_font_size": {
                                    "unit": "em",
                                    "size": 1.1111,
                                    "sizes": []
                                },
                                "typography_font_weight": "600",
                                "typography_text_transform": "capitalize",
                                "typography_font_style": "normal",
                                "typography_text_decoration": "none",
                                "typography_line_height": {
                                    "unit": "em",
                                    "size": 1,
                                    "sizes": []
                                },
                                "typography_letter_spacing": {
                                    "unit": "px",
                                    "size": 0,
                                    "sizes": []
                                },
                                "button_text_color": "#0C0C0C",
                                "background_color": "#FFFFFF",
                                "hover_color": "#FFFFFF",
                                "button_background_hover_color": "#0C0C0C",
                                "border_border": "solid",
                                "border_width": {
                                    "unit": "px",
                                    "top": "2",
                                    "right": "2",
                                    "bottom": "2",
                                    "left": "2",
                                    "isLinked": false
                                },
                                "border_color": "#0C0C0C",
                                "border_radius": {
                                    "unit": "px",
                                    "top": "8",
                                    "right": "8",
                                    "bottom": "8",
                                    "left": "8",
                                    "isLinked": true
                                },
                                "text_padding": {
                                    "unit": "px",
                                    "top": "24",
                                    "right": "58",
                                    "bottom": "23",
                                    "left": "58",
                                    "isLinked": false
                                },
                                "_margin": {
                                    "unit": "px",
                                    "top": "0",
                                    "right": "0",
                                    "bottom": "0",
                                    "left": "0",
                                    "isLinked": false
                                },
                                "_padding": {
                                    "unit": "px",
                                    "top": "0",
                                    "right": "0",
                                    "bottom": "0",
                                    "left": "0",
                                    "isLinked": false
                                },
                                "_animation": "fadeIn",
                                "border_width_mobile": {
                                    "unit": "px",
                                    "top": "2",
                                    "right": "2",
                                    "bottom": "2",
                                    "left": "2",
                                    "isLinked": true
                                },
                                "text_padding_mobile": {
                                    "unit": "px",
                                    "top": "18",
                                    "right": "50",
                                    "bottom": "18",
                                    "left": "50",
                                    "isLinked": false
                                },
                                "_margin_mobile": {
                                    "unit": "px",
                                    "top": "0",
                                    "right": "0",
                                    "bottom": "0",
                                    "left": "0",
                                    "isLinked": false
                                },
                                "_padding_mobile": {
                                    "unit": "px",
                                    "top": "0",
                                    "right": "0",
                                    "bottom": "0",
                                    "left": "0",
                                    "isLinked": false
                                },
                                "_animation_mobile": "fadeIn",
                                "typography_font_family": "Josefin Sans"
                            },
                            "elements": [],
                            "isInner": false,
                            "widgetType": "button",
                            "elType": "widget"
                        }
                    ],
                    "isInner": false,
                    "elType": "column"
                }
            ],
            "isInner": false,
            "elType": "section"
        }
    ]
}