{
    "version": "0.4",
    "title": "Portosia &#8211; Pricing",
    "type": "page",
    "metadata": {
        "template_type": "single-page",
        "include_in_zip": "1",
        "elementor_pro_required": null,
        "wp_page_template": "default"
    },
    "content": [
        {
            "id": "46d2e6c5",
            "settings": {
                "background_background": "classic",
                "background_image": {
                    "url": "https:\/\/template-kit.rootlayers.com\/portosia\/wp-content\/uploads\/sites\/4\/2020\/10\/bg-header.png",
                    "id": 168
                },
                "padding": {
                    "unit": "em",
                    "top": "6",
                    "right": "0",
                    "bottom": "5",
                    "left": "0",
                    "isLinked": false
                },
                "__globals__": {
                    "background_color": ""
                },
                "background_position": "bottom center",
                "background_ypos": {
                    "unit": "px",
                    "size": 141,
                    "sizes": []
                },
                "background_repeat": "no-repeat",
                "padding_mobile": {
                    "unit": "em",
                    "top": "3",
                    "right": "0",
                    "bottom": "3",
                    "left": "0",
                    "isLinked": false
                },
                "background_color": "#F2EFEF"
            },
            "elements": [
                {
                    "id": "462bf271",
                    "settings": {
                        "_column_size": 100,
                        "_inline_size": null
                    },
                    "elements": [
                        {
                            "id": "7fd80e50",
                            "settings": {
                                "title": "Pricing",
                                "typography_typography": "custom",
                                "typography_font_family": "Poppins",
                                "typography_font_size": {
                                    "unit": "px",
                                    "size": 18,
                                    "sizes": []
                                },
                                "typography_font_weight": "500",
                                "typography_line_height": {
                                    "unit": "em",
                                    "size": 1.1999999999999999555910790149937383830547332763671875,
                                    "sizes": []
                                },
                                "__globals__": {
                                    "title_color": "globals\/colors?id=e28396d"
                                },
                                "header_size": "div",
                                "_animation": "fadeInLeft",
                                "align": "center"
                            },
                            "elements": [],
                            "isInner": false,
                            "widgetType": "heading",
                            "elType": "widget"
                        },
                        {
                            "id": "5ac1ac5e",
                            "settings": {
                                "title": "Best Plan for Your Need.",
                                "align": "center",
                                "title_color": "#000000",
                                "typography_typography": "custom",
                                "typography_font_family": "Poppins",
                                "typography_font_size": {
                                    "unit": "px",
                                    "size": 52,
                                    "sizes": []
                                },
                                "typography_font_size_mobile": {
                                    "unit": "px",
                                    "size": 42,
                                    "sizes": []
                                },
                                "typography_font_weight": "600",
                                "typography_line_height": {
                                    "unit": "em",
                                    "size": 1.3000000000000000444089209850062616169452667236328125,
                                    "sizes": []
                                },
                                "_animation": "fadeInUp",
                                "__globals__": {
                                    "title_color": ""
                                }
                            },
                            "elements": [],
                            "isInner": false,
                            "widgetType": "heading",
                            "elType": "widget"
                        },
                        {
                            "id": "19aaf40e",
                            "settings": {
                                "align": "center",
                                "typography_typography": "custom",
                                "typography_font_family": "Poppins",
                                "typography_font_size": {
                                    "unit": "px",
                                    "size": 16,
                                    "sizes": []
                                },
                                "typography_font_weight": "400",
                                "typography_line_height": {
                                    "unit": "em",
                                    "size": 1.5,
                                    "sizes": []
                                },
                                "_margin": {
                                    "unit": "px",
                                    "top": "0",
                                    "right": "0",
                                    "bottom": "0",
                                    "left": "0",
                                    "isLinked": false
                                },
                                "_margin_tablet": {
                                    "unit": "px",
                                    "top": "0",
                                    "right": "0",
                                    "bottom": "0",
                                    "left": "0",
                                    "isLinked": true
                                },
                                "_margin_mobile": {
                                    "unit": "px",
                                    "top": "0",
                                    "right": "0",
                                    "bottom": "0",
                                    "left": "0",
                                    "isLinked": false
                                },
                                "__globals__": {
                                    "text_color": ""
                                },
                                "editor": "<p>Lorem ipsum dolor sit amet, consectetur adipiscing elit.<br \/>Ut elit tellus, luctus nec ullamcorper mattis, pulvinar dapibus leo.<\/p>",
                                "_animation": "fadeInUp"
                            },
                            "elements": [],
                            "isInner": false,
                            "widgetType": "text-editor",
                            "elType": "widget"
                        }
                    ],
                    "isInner": false,
                    "elType": "column"
                }
            ],
            "isInner": false,
            "elType": "section"
        },
        {
            "id": "72136ced",
            "settings": {
                "structure": "30",
                "padding": {
                    "unit": "em",
                    "top": "7",
                    "right": "0",
                    "bottom": "3",
                    "left": "0",
                    "isLinked": false
                },
                "padding_mobile": {
                    "unit": "em",
                    "top": "4",
                    "right": "0",
                    "bottom": "0",
                    "left": "0",
                    "isLinked": false
                }
            },
            "elements": [
                {
                    "id": "3c525e65",
                    "settings": {
                        "_column_size": 33,
                        "_inline_size": null
                    },
                    "elements": [
                        {
                            "id": "1cb307cb",
                            "settings": {
                                "border_radius": {
                                    "unit": "px",
                                    "top": "32",
                                    "right": "32",
                                    "bottom": "32",
                                    "left": "32",
                                    "isLinked": true
                                },
                                "box_shadow_box_shadow_type": "yes",
                                "box_shadow_box_shadow": {
                                    "horizontal": 0,
                                    "vertical": 1,
                                    "blur": 19,
                                    "spread": 0,
                                    "color": "rgba(0, 0, 0, 0.15)"
                                },
                                "margin": {
                                    "unit": "px",
                                    "top": "0",
                                    "right": 0,
                                    "bottom": "5",
                                    "left": 0,
                                    "isLinked": false
                                },
                                "padding": {
                                    "unit": "px",
                                    "top": "40",
                                    "right": "35",
                                    "bottom": "40",
                                    "left": "35",
                                    "isLinked": false
                                },
                                "padding_tablet": {
                                    "unit": "px",
                                    "top": "30",
                                    "right": "15",
                                    "bottom": "30",
                                    "left": "15",
                                    "isLinked": false
                                },
                                "animation": "zoomIn"
                            },
                            "elements": [
                                {
                                    "id": "75d0a69c",
                                    "settings": {
                                        "_column_size": 100,
                                        "_inline_size": null
                                    },
                                    "elements": [
                                        {
                                            "id": "33bdc0f",
                                            "settings": {
                                                "title": "Personal",
                                                "header_size": "h3",
                                                "title_color": "#000000",
                                                "typography_typography": "custom",
                                                "typography_font_family": "Poppins",
                                                "typography_font_size": {
                                                    "unit": "px",
                                                    "size": 28,
                                                    "sizes": []
                                                },
                                                "typography_font_weight": "600",
                                                "typography_line_height": {
                                                    "unit": "em",
                                                    "size": 1.3000000000000000444089209850062616169452667236328125,
                                                    "sizes": []
                                                }
                                            },
                                            "elements": [],
                                            "isInner": false,
                                            "widgetType": "heading",
                                            "elType": "widget"
                                        },
                                        {
                                            "id": "42bc7f74",
                                            "settings": {
                                                "title": "Room To Grow",
                                                "header_size": "div",
                                                "typography_typography": "custom",
                                                "typography_font_family": "Poppins",
                                                "typography_font_size": {
                                                    "unit": "px",
                                                    "size": 14,
                                                    "sizes": []
                                                },
                                                "typography_font_weight": "400",
                                                "_margin": {
                                                    "unit": "px",
                                                    "top": "-14",
                                                    "right": "0",
                                                    "bottom": "0",
                                                    "left": "0",
                                                    "isLinked": false
                                                },
                                                "__globals__": {
                                                    "title_color": "globals\/colors?id=4fcd6a7"
                                                }
                                            },
                                            "elements": [],
                                            "isInner": false,
                                            "widgetType": "heading",
                                            "elType": "widget"
                                        },
                                        {
                                            "id": "38e55a7e",
                                            "settings": {
                                                "title": "$5.9",
                                                "header_size": "span",
                                                "typography_typography": "custom",
                                                "typography_font_family": "Poppins",
                                                "typography_font_size": {
                                                    "unit": "px",
                                                    "size": 28,
                                                    "sizes": []
                                                },
                                                "typography_font_weight": "600",
                                                "_margin": {
                                                    "unit": "px",
                                                    "top": "10",
                                                    "right": "0",
                                                    "bottom": "20",
                                                    "left": "0",
                                                    "isLinked": false
                                                },
                                                "__globals__": {
                                                    "title_color": "globals\/colors?id=e28396d"
                                                }
                                            },
                                            "elements": [],
                                            "isInner": false,
                                            "widgetType": "heading",
                                            "elType": "widget"
                                        },
                                        {
                                            "id": "137deced",
                                            "settings": {
                                                "icon_list": [
                                                    {
                                                        "text": "Lorem ipsum dolor amet adi ciptum ora ena nase.",
                                                        "selected_icon": {
                                                            "value": "fas fa-check-circle",
                                                            "library": "fa-solid"
                                                        },
                                                        "_id": "cab4509"
                                                    },
                                                    {
                                                        "text": "Lorem ipsum dolor amet adi ciptum ora ena nase.",
                                                        "selected_icon": {
                                                            "value": "fas fa-check-circle",
                                                            "library": "fa-solid"
                                                        },
                                                        "_id": "efc8883"
                                                    },
                                                    {
                                                        "text": "Lorem ipsum dolor amet adi ciptum ora ena nase.",
                                                        "selected_icon": {
                                                            "value": "fas fa-check-circle",
                                                            "library": "fa-solid"
                                                        },
                                                        "_id": "fdf21c7"
                                                    }
                                                ],
                                                "space_between": {
                                                    "unit": "px",
                                                    "size": 15,
                                                    "sizes": []
                                                },
                                                "icon_size": {
                                                    "unit": "px",
                                                    "size": 28,
                                                    "sizes": []
                                                },
                                                "icon_typography_typography": "custom",
                                                "icon_typography_font_family": "Poppins",
                                                "icon_typography_font_size": {
                                                    "unit": "px",
                                                    "size": 14,
                                                    "sizes": []
                                                },
                                                "icon_typography_font_weight": "400",
                                                "_margin": {
                                                    "unit": "px",
                                                    "top": "0",
                                                    "right": "0",
                                                    "bottom": "030",
                                                    "left": "0",
                                                    "isLinked": false
                                                },
                                                "__globals__": {
                                                    "icon_color": "globals\/colors?id=e28396d",
                                                    "text_color": "globals\/colors?id=4fcd6a7"
                                                }
                                            },
                                            "elements": [],
                                            "isInner": false,
                                            "widgetType": "icon-list",
                                            "elType": "widget"
                                        },
                                        {
                                            "id": "13f8e811",
                                            "settings": {
                                                "text": "Select Plan",
                                                "align": "center",
                                                "size": "xl",
                                                "typography_typography": "custom",
                                                "typography_font_family": "Poppins",
                                                "typography_font_size": {
                                                    "unit": "px",
                                                    "size": 16,
                                                    "sizes": []
                                                },
                                                "typography_font_weight": "500",
                                                "hover_animation": "float",
                                                "border_radius": {
                                                    "unit": "px",
                                                    "top": "15",
                                                    "right": "15",
                                                    "bottom": "15",
                                                    "left": "15",
                                                    "isLinked": true
                                                },
                                                "__globals__": {
                                                    "background_color": "globals\/colors?id=e28396d"
                                                }
                                            },
                                            "elements": [],
                                            "isInner": false,
                                            "widgetType": "button",
                                            "elType": "widget"
                                        }
                                    ],
                                    "isInner": true,
                                    "elType": "column"
                                }
                            ],
                            "isInner": true,
                            "elType": "section"
                        }
                    ],
                    "isInner": false,
                    "elType": "column"
                },
                {
                    "id": "64f3df3d",
                    "settings": {
                        "_column_size": 33,
                        "_inline_size": null
                    },
                    "elements": [
                        {
                            "id": "6e585131",
                            "settings": {
                                "background_background": "classic",
                                "border_radius": {
                                    "unit": "px",
                                    "top": "32",
                                    "right": "32",
                                    "bottom": "32",
                                    "left": "32",
                                    "isLinked": true
                                },
                                "box_shadow_box_shadow_type": "yes",
                                "box_shadow_box_shadow": {
                                    "horizontal": 0,
                                    "vertical": 1,
                                    "blur": 19,
                                    "spread": 0,
                                    "color": "rgba(0, 0, 0, 0.15)"
                                },
                                "margin": {
                                    "unit": "px",
                                    "top": "0",
                                    "right": 0,
                                    "bottom": "5",
                                    "left": 0,
                                    "isLinked": false
                                },
                                "padding": {
                                    "unit": "px",
                                    "top": "40",
                                    "right": "35",
                                    "bottom": "40",
                                    "left": "35",
                                    "isLinked": false
                                },
                                "padding_tablet": {
                                    "unit": "px",
                                    "top": "30",
                                    "right": "15",
                                    "bottom": "30",
                                    "left": "15",
                                    "isLinked": false
                                },
                                "animation": "zoomIn",
                                "animation_delay": 200,
                                "__globals__": {
                                    "background_color": "globals\/colors?id=e28396d"
                                }
                            },
                            "elements": [
                                {
                                    "id": "861c1d5",
                                    "settings": {
                                        "_column_size": 100,
                                        "_inline_size": null
                                    },
                                    "elements": [
                                        {
                                            "id": "310c4b58",
                                            "settings": {
                                                "title": "Professional",
                                                "header_size": "h3",
                                                "title_color": "#FFFFFF",
                                                "typography_typography": "custom",
                                                "typography_font_family": "Poppins",
                                                "typography_font_size": {
                                                    "unit": "px",
                                                    "size": 28,
                                                    "sizes": []
                                                },
                                                "typography_font_weight": "600",
                                                "typography_line_height": {
                                                    "unit": "em",
                                                    "size": 1.3000000000000000444089209850062616169452667236328125,
                                                    "sizes": []
                                                }
                                            },
                                            "elements": [],
                                            "isInner": false,
                                            "widgetType": "heading",
                                            "elType": "widget"
                                        },
                                        {
                                            "id": "47faa1dc",
                                            "settings": {
                                                "title": "Road To Pro",
                                                "header_size": "div",
                                                "title_color": "#F5F5F5",
                                                "typography_typography": "custom",
                                                "typography_font_family": "Poppins",
                                                "typography_font_size": {
                                                    "unit": "px",
                                                    "size": 14,
                                                    "sizes": []
                                                },
                                                "typography_font_weight": "400",
                                                "_margin": {
                                                    "unit": "px",
                                                    "top": "-14",
                                                    "right": "0",
                                                    "bottom": "0",
                                                    "left": "0",
                                                    "isLinked": false
                                                },
                                                "__globals__": {
                                                    "title_color": ""
                                                }
                                            },
                                            "elements": [],
                                            "isInner": false,
                                            "widgetType": "heading",
                                            "elType": "widget"
                                        },
                                        {
                                            "id": "153cb6f1",
                                            "settings": {
                                                "title": "$19.9",
                                                "header_size": "span",
                                                "title_color": "#FFFFFF",
                                                "typography_typography": "custom",
                                                "typography_font_family": "Poppins",
                                                "typography_font_size": {
                                                    "unit": "px",
                                                    "size": 28,
                                                    "sizes": []
                                                },
                                                "typography_font_weight": "600",
                                                "_margin": {
                                                    "unit": "px",
                                                    "top": "10",
                                                    "right": "0",
                                                    "bottom": "20",
                                                    "left": "0",
                                                    "isLinked": false
                                                },
                                                "__globals__": {
                                                    "title_color": ""
                                                }
                                            },
                                            "elements": [],
                                            "isInner": false,
                                            "widgetType": "heading",
                                            "elType": "widget"
                                        },
                                        {
                                            "id": "62b90787",
                                            "settings": {
                                                "icon_list": [
                                                    {
                                                        "text": "Lorem ipsum dolor amet adi ciptum ora ena nase.",
                                                        "selected_icon": {
                                                            "value": "fas fa-check-circle",
                                                            "library": "fa-solid"
                                                        },
                                                        "_id": "cab4509"
                                                    },
                                                    {
                                                        "text": "Lorem ipsum dolor amet adi ciptum ora ena nase.",
                                                        "selected_icon": {
                                                            "value": "fas fa-check-circle",
                                                            "library": "fa-solid"
                                                        },
                                                        "_id": "efc8883"
                                                    },
                                                    {
                                                        "text": "Lorem ipsum dolor amet adi ciptum ora ena nase.",
                                                        "selected_icon": {
                                                            "value": "fas fa-check-circle",
                                                            "library": "fa-solid"
                                                        },
                                                        "_id": "fdf21c7"
                                                    }
                                                ],
                                                "space_between": {
                                                    "unit": "px",
                                                    "size": 15,
                                                    "sizes": []
                                                },
                                                "icon_color": "#FFFFFF",
                                                "icon_size": {
                                                    "unit": "px",
                                                    "size": 28,
                                                    "sizes": []
                                                },
                                                "text_color": "#F5F5F5",
                                                "icon_typography_typography": "custom",
                                                "icon_typography_font_family": "Poppins",
                                                "icon_typography_font_size": {
                                                    "unit": "px",
                                                    "size": 14,
                                                    "sizes": []
                                                },
                                                "icon_typography_font_weight": "400",
                                                "_margin": {
                                                    "unit": "px",
                                                    "top": "0",
                                                    "right": "0",
                                                    "bottom": "030",
                                                    "left": "0",
                                                    "isLinked": false
                                                },
                                                "__globals__": {
                                                    "icon_color": "",
                                                    "text_color": ""
                                                }
                                            },
                                            "elements": [],
                                            "isInner": false,
                                            "widgetType": "icon-list",
                                            "elType": "widget"
                                        },
                                        {
                                            "id": "5bfdf0dc",
                                            "settings": {
                                                "text": "Select Plan",
                                                "align": "center",
                                                "size": "xl",
                                                "typography_typography": "custom",
                                                "typography_font_family": "Poppins",
                                                "typography_font_size": {
                                                    "unit": "px",
                                                    "size": 16,
                                                    "sizes": []
                                                },
                                                "typography_font_weight": "500",
                                                "background_color": "#FFFFFF",
                                                "hover_animation": "float",
                                                "border_radius": {
                                                    "unit": "px",
                                                    "top": "15",
                                                    "right": "15",
                                                    "bottom": "15",
                                                    "left": "15",
                                                    "isLinked": true
                                                },
                                                "__globals__": {
                                                    "background_color": "",
                                                    "button_text_color": "globals\/colors?id=e28396d"
                                                }
                                            },
                                            "elements": [],
                                            "isInner": false,
                                            "widgetType": "button",
                                            "elType": "widget"
                                        }
                                    ],
                                    "isInner": true,
                                    "elType": "column"
                                }
                            ],
                            "isInner": true,
                            "elType": "section"
                        }
                    ],
                    "isInner": false,
                    "elType": "column"
                },
                {
                    "id": "2fb2ce50",
                    "settings": {
                        "_column_size": 33,
                        "_inline_size": null
                    },
                    "elements": [
                        {
                            "id": "ca27542",
                            "settings": {
                                "border_radius": {
                                    "unit": "px",
                                    "top": "32",
                                    "right": "32",
                                    "bottom": "32",
                                    "left": "32",
                                    "isLinked": true
                                },
                                "box_shadow_box_shadow_type": "yes",
                                "box_shadow_box_shadow": {
                                    "horizontal": 0,
                                    "vertical": 1,
                                    "blur": 19,
                                    "spread": 0,
                                    "color": "rgba(0, 0, 0, 0.15)"
                                },
                                "margin": {
                                    "unit": "px",
                                    "top": "0",
                                    "right": 0,
                                    "bottom": "5",
                                    "left": 0,
                                    "isLinked": false
                                },
                                "padding": {
                                    "unit": "px",
                                    "top": "40",
                                    "right": "35",
                                    "bottom": "40",
                                    "left": "35",
                                    "isLinked": false
                                },
                                "padding_tablet": {
                                    "unit": "px",
                                    "top": "30",
                                    "right": "15",
                                    "bottom": "30",
                                    "left": "15",
                                    "isLinked": false
                                },
                                "animation": "zoomIn",
                                "animation_delay": 400
                            },
                            "elements": [
                                {
                                    "id": "3b261467",
                                    "settings": {
                                        "_column_size": 100,
                                        "_inline_size": null
                                    },
                                    "elements": [
                                        {
                                            "id": "233478eb",
                                            "settings": {
                                                "title": "Business",
                                                "header_size": "h3",
                                                "title_color": "#000000",
                                                "typography_typography": "custom",
                                                "typography_font_family": "Poppins",
                                                "typography_font_size": {
                                                    "unit": "px",
                                                    "size": 28,
                                                    "sizes": []
                                                },
                                                "typography_font_weight": "600",
                                                "typography_line_height": {
                                                    "unit": "em",
                                                    "size": 1.3000000000000000444089209850062616169452667236328125,
                                                    "sizes": []
                                                }
                                            },
                                            "elements": [],
                                            "isInner": false,
                                            "widgetType": "heading",
                                            "elType": "widget"
                                        },
                                        {
                                            "id": "1b16fc38",
                                            "settings": {
                                                "title": "Advance Features",
                                                "header_size": "div",
                                                "typography_typography": "custom",
                                                "typography_font_family": "Poppins",
                                                "typography_font_size": {
                                                    "unit": "px",
                                                    "size": 14,
                                                    "sizes": []
                                                },
                                                "typography_font_weight": "400",
                                                "_margin": {
                                                    "unit": "px",
                                                    "top": "-14",
                                                    "right": "0",
                                                    "bottom": "0",
                                                    "left": "0",
                                                    "isLinked": false
                                                },
                                                "__globals__": {
                                                    "title_color": "globals\/colors?id=4fcd6a7"
                                                }
                                            },
                                            "elements": [],
                                            "isInner": false,
                                            "widgetType": "heading",
                                            "elType": "widget"
                                        },
                                        {
                                            "id": "4536992f",
                                            "settings": {
                                                "title": "$99",
                                                "header_size": "span",
                                                "typography_typography": "custom",
                                                "typography_font_family": "Poppins",
                                                "typography_font_size": {
                                                    "unit": "px",
                                                    "size": 28,
                                                    "sizes": []
                                                },
                                                "typography_font_weight": "600",
                                                "_margin": {
                                                    "unit": "px",
                                                    "top": "10",
                                                    "right": "0",
                                                    "bottom": "20",
                                                    "left": "0",
                                                    "isLinked": false
                                                },
                                                "__globals__": {
                                                    "title_color": "globals\/colors?id=e28396d"
                                                }
                                            },
                                            "elements": [],
                                            "isInner": false,
                                            "widgetType": "heading",
                                            "elType": "widget"
                                        },
                                        {
                                            "id": "4b282170",
                                            "settings": {
                                                "icon_list": [
                                                    {
                                                        "text": "Lorem ipsum dolor amet adi ciptum ora ena nase.",
                                                        "selected_icon": {
                                                            "value": "fas fa-check-circle",
                                                            "library": "fa-solid"
                                                        },
                                                        "_id": "cab4509"
                                                    },
                                                    {
                                                        "text": "Lorem ipsum dolor amet adi ciptum ora ena nase.",
                                                        "selected_icon": {
                                                            "value": "fas fa-check-circle",
                                                            "library": "fa-solid"
                                                        },
                                                        "_id": "efc8883"
                                                    },
                                                    {
                                                        "text": "Lorem ipsum dolor amet adi ciptum ora ena nase.",
                                                        "selected_icon": {
                                                            "value": "fas fa-check-circle",
                                                            "library": "fa-solid"
                                                        },
                                                        "_id": "fdf21c7"
                                                    }
                                                ],
                                                "space_between": {
                                                    "unit": "px",
                                                    "size": 15,
                                                    "sizes": []
                                                },
                                                "icon_size": {
                                                    "unit": "px",
                                                    "size": 28,
                                                    "sizes": []
                                                },
                                                "icon_typography_typography": "custom",
                                                "icon_typography_font_family": "Poppins",
                                                "icon_typography_font_size": {
                                                    "unit": "px",
                                                    "size": 14,
                                                    "sizes": []
                                                },
                                                "icon_typography_font_weight": "400",
                                                "_margin": {
                                                    "unit": "px",
                                                    "top": "0",
                                                    "right": "0",
                                                    "bottom": "030",
                                                    "left": "0",
                                                    "isLinked": false
                                                },
                                                "__globals__": {
                                                    "icon_color": "globals\/colors?id=e28396d",
                                                    "text_color": "globals\/colors?id=4fcd6a7"
                                                }
                                            },
                                            "elements": [],
                                            "isInner": false,
                                            "widgetType": "icon-list",
                                            "elType": "widget"
                                        },
                                        {
                                            "id": "137e1e1f",
                                            "settings": {
                                                "text": "Select Plan",
                                                "align": "center",
                                                "size": "xl",
                                                "typography_typography": "custom",
                                                "typography_font_family": "Poppins",
                                                "typography_font_size": {
                                                    "unit": "px",
                                                    "size": 16,
                                                    "sizes": []
                                                },
                                                "typography_font_weight": "500",
                                                "hover_animation": "float",
                                                "border_radius": {
                                                    "unit": "px",
                                                    "top": "15",
                                                    "right": "15",
                                                    "bottom": "15",
                                                    "left": "15",
                                                    "isLinked": true
                                                },
                                                "__globals__": {
                                                    "background_color": "globals\/colors?id=e28396d"
                                                }
                                            },
                                            "elements": [],
                                            "isInner": false,
                                            "widgetType": "button",
                                            "elType": "widget"
                                        }
                                    ],
                                    "isInner": true,
                                    "elType": "column"
                                }
                            ],
                            "isInner": true,
                            "elType": "section"
                        }
                    ],
                    "isInner": false,
                    "elType": "column"
                }
            ],
            "isInner": false,
            "elType": "section"
        },
        {
            "id": "6b3dbe1a",
            "settings": {
                "padding": {
                    "unit": "em",
                    "top": "3",
                    "right": "0",
                    "bottom": "0",
                    "left": "0",
                    "isLinked": false
                }
            },
            "elements": [
                {
                    "id": "67040f28",
                    "settings": {
                        "_column_size": 100,
                        "_inline_size": null
                    },
                    "elements": [
                        {
                            "id": "7d90bfda",
                            "settings": {
                                "image": {
                                    "url": "https:\/\/template-kit.rootlayers.com\/portosia\/wp-content\/uploads\/sites\/4\/2020\/10\/circle-yellow.png",
                                    "id": 85
                                },
                                "_element_width": "auto",
                                "_position": "absolute",
                                "_offset_orientation_h": "end",
                                "_offset_x_end": {
                                    "unit": "px",
                                    "size": 334,
                                    "sizes": []
                                },
                                "_offset_x_end_tablet": {
                                    "unit": "px",
                                    "size": 196.5,
                                    "sizes": []
                                },
                                "_offset_x_end_mobile": {
                                    "unit": "px",
                                    "size": 20.699999999999999289457264239899814128875732421875,
                                    "sizes": []
                                },
                                "_offset_y_tablet": {
                                    "unit": "px",
                                    "size": -31,
                                    "sizes": []
                                }
                            },
                            "elements": [],
                            "isInner": false,
                            "widgetType": "image",
                            "elType": "widget"
                        },
                        {
                            "id": "19f230cb",
                            "settings": {
                                "title": "FAQ",
                                "align": "center",
                                "typography_typography": "custom",
                                "typography_font_family": "Poppins",
                                "typography_font_size": {
                                    "unit": "px",
                                    "size": 20,
                                    "sizes": []
                                },
                                "typography_font_weight": "500",
                                "typography_line_height": {
                                    "unit": "em",
                                    "size": 1.1999999999999999555910790149937383830547332763671875,
                                    "sizes": []
                                },
                                "__globals__": {
                                    "title_color": "globals\/colors?id=e28396d"
                                },
                                "_animation": "fadeInUp",
                                "_z_index": 1
                            },
                            "elements": [],
                            "isInner": false,
                            "widgetType": "heading",
                            "elType": "widget"
                        },
                        {
                            "id": "706a9d16",
                            "settings": {
                                "title": "Frequently Asked<br>Questions.",
                                "align": "center",
                                "title_color": "#000000",
                                "typography_typography": "custom",
                                "typography_font_family": "Poppins",
                                "typography_font_size": {
                                    "unit": "px",
                                    "size": 42,
                                    "sizes": []
                                },
                                "typography_font_size_tablet": {
                                    "unit": "px",
                                    "size": 32,
                                    "sizes": []
                                },
                                "typography_font_weight": "600",
                                "typography_line_height": {
                                    "unit": "em",
                                    "size": 1.3000000000000000444089209850062616169452667236328125,
                                    "sizes": []
                                },
                                "__globals__": {
                                    "title_color": ""
                                },
                                "_animation": "fadeInUp",
                                "_z_index": 1
                            },
                            "elements": [],
                            "isInner": false,
                            "widgetType": "heading",
                            "elType": "widget"
                        },
                        {
                            "id": "3e96aced",
                            "settings": {
                                "align": "center",
                                "typography_typography": "custom",
                                "typography_font_family": "Poppins",
                                "typography_font_size": {
                                    "unit": "px",
                                    "size": 16,
                                    "sizes": []
                                },
                                "typography_font_weight": "400",
                                "typography_line_height": {
                                    "unit": "em",
                                    "size": 1.5,
                                    "sizes": []
                                },
                                "_margin": {
                                    "unit": "px",
                                    "top": "0",
                                    "right": "280",
                                    "bottom": "0",
                                    "left": "280",
                                    "isLinked": false
                                },
                                "_margin_tablet": {
                                    "unit": "px",
                                    "top": "0",
                                    "right": "120",
                                    "bottom": "0",
                                    "left": "120",
                                    "isLinked": false
                                },
                                "_margin_mobile": {
                                    "unit": "px",
                                    "top": "0",
                                    "right": "0",
                                    "bottom": "0",
                                    "left": "0",
                                    "isLinked": false
                                },
                                "__globals__": {
                                    "text_color": "globals\/colors?id=4fcd6a7"
                                },
                                "_animation": "fadeInUp",
                                "_z_index": 1
                            },
                            "elements": [],
                            "isInner": false,
                            "widgetType": "text-editor",
                            "elType": "widget"
                        }
                    ],
                    "isInner": false,
                    "elType": "column"
                }
            ],
            "isInner": false,
            "elType": "section"
        },
        {
            "id": "3abcdc0a",
            "settings": {
                "structure": "20",
                "padding": {
                    "unit": "em",
                    "top": "3",
                    "right": "0",
                    "bottom": "6",
                    "left": "0",
                    "isLinked": false
                },
                "padding_mobile": {
                    "unit": "em",
                    "top": "3",
                    "right": "0",
                    "bottom": "2",
                    "left": "0",
                    "isLinked": false
                }
            },
            "elements": [
                {
                    "id": "32350eb6",
                    "settings": {
                        "_column_size": 50,
                        "_inline_size": null
                    },
                    "elements": [
                        {
                            "id": "66e84821",
                            "settings": {
                                "tabs": [
                                    {
                                        "tab_title": "How To Create Blog From Start With WordPress?",
                                        "tab_content": "Lorem ipsum dolor sit amet, consectetur adipiscing elit. Ut elit tellus, luctus nec ullamcorper mattis, pulvinar dapibus leo.",
                                        "_id": "33c3a98"
                                    },
                                    {
                                        "tab_title": "Move Header To Top of Page Menu?",
                                        "tab_content": "Lorem ipsum dolor sit amet, consectetur adipiscing elit. Ut elit tellus, luctus nec ullamcorper mattis, pulvinar dapibus leo.",
                                        "_id": "069960b"
                                    },
                                    {
                                        "tab_title": "Disable Menu When Active Scroll?",
                                        "tab_content": "Lorem ipsum dolor sit amet, consectetur adipiscing elit. Ut elit tellus, luctus nec ullamcorper mattis, pulvinar dapibus leo.",
                                        "_id": "bc2a029"
                                    },
                                    {
                                        "tab_title": "Change Background Image on Landing Page?",
                                        "tab_content": "Lorem ipsum dolor sit amet, consectetur adipiscing elit. Ut elit tellus, luctus nec ullamcorper mattis, pulvinar dapibus leo.",
                                        "_id": "e09e099"
                                    }
                                ],
                                "selected_icon": {
                                    "value": "fas fa-chevron-down",
                                    "library": "fa-solid"
                                },
                                "selected_active_icon": {
                                    "value": "fas fa-chevron-up",
                                    "library": "fa-solid"
                                },
                                "border_width": {
                                    "unit": "px",
                                    "size": 0,
                                    "sizes": []
                                },
                                "space_between": {
                                    "unit": "px",
                                    "size": 25,
                                    "sizes": []
                                },
                                "title_background": "#F5F7FA",
                                "title_color": "#000000",
                                "title_typography_typography": "custom",
                                "title_typography_font_family": "Poppins",
                                "title_typography_font_weight": "500",
                                "title_typography_line_height": {
                                    "unit": "em",
                                    "size": 1.3000000000000000444089209850062616169452667236328125,
                                    "sizes": []
                                },
                                "title_padding": {
                                    "unit": "px",
                                    "top": "30",
                                    "right": "25",
                                    "bottom": "30",
                                    "left": "25",
                                    "isLinked": false
                                },
                                "icon_align": "right",
                                "icon_space": {
                                    "unit": "px",
                                    "size": 0,
                                    "sizes": []
                                },
                                "content_background_color": "#F5F7FA",
                                "content_typography_typography": "custom",
                                "content_typography_font_family": "Poppins",
                                "content_typography_font_weight": "400",
                                "content_padding": {
                                    "unit": "px",
                                    "top": "10",
                                    "right": "25",
                                    "bottom": "25",
                                    "left": "25",
                                    "isLinked": false
                                },
                                "_animation": "fadeInUp",
                                "__globals__": {
                                    "tab_active_color": "globals\/colors?id=e28396d"
                                }
                            },
                            "elements": [],
                            "isInner": false,
                            "widgetType": "toggle",
                            "elType": "widget"
                        }
                    ],
                    "isInner": false,
                    "elType": "column"
                },
                {
                    "id": "a706a54",
                    "settings": {
                        "_column_size": 50,
                        "_inline_size": null
                    },
                    "elements": [
                        {
                            "id": "168b49b9",
                            "settings": {
                                "tabs": [
                                    {
                                        "tab_title": "Disable Menu When Active Scroll?",
                                        "tab_content": "Lorem ipsum dolor sit amet, consectetur adipiscing elit. Ut elit tellus, luctus nec ullamcorper mattis, pulvinar dapibus leo.",
                                        "_id": "bc2a029"
                                    },
                                    {
                                        "tab_title": "Move Header To Top of Page Menu?",
                                        "tab_content": "Lorem ipsum dolor sit amet, consectetur adipiscing elit. Ut elit tellus, luctus nec ullamcorper mattis, pulvinar dapibus leo.",
                                        "_id": "069960b"
                                    },
                                    {
                                        "tab_title": "How To Create Blog From Start With WordPress?",
                                        "tab_content": "Lorem ipsum dolor sit amet, consectetur adipiscing elit. Ut elit tellus, luctus nec ullamcorper mattis, pulvinar dapibus leo.",
                                        "_id": "33c3a98"
                                    },
                                    {
                                        "tab_title": "Change Background Image on Landing Page?",
                                        "tab_content": "Lorem ipsum dolor sit amet, consectetur adipiscing elit. Ut elit tellus, luctus nec ullamcorper mattis, pulvinar dapibus leo.",
                                        "_id": "e09e099"
                                    }
                                ],
                                "selected_icon": {
                                    "value": "fas fa-chevron-down",
                                    "library": "fa-solid"
                                },
                                "selected_active_icon": {
                                    "value": "fas fa-chevron-up",
                                    "library": "fa-solid"
                                },
                                "border_width": {
                                    "unit": "px",
                                    "size": 0,
                                    "sizes": []
                                },
                                "space_between": {
                                    "unit": "px",
                                    "size": 25,
                                    "sizes": []
                                },
                                "title_background": "#F5F7FA",
                                "title_color": "#000000",
                                "title_typography_typography": "custom",
                                "title_typography_font_family": "Poppins",
                                "title_typography_font_weight": "500",
                                "title_typography_line_height": {
                                    "unit": "em",
                                    "size": 1.3000000000000000444089209850062616169452667236328125,
                                    "sizes": []
                                },
                                "title_padding": {
                                    "unit": "px",
                                    "top": "30",
                                    "right": "25",
                                    "bottom": "30",
                                    "left": "25",
                                    "isLinked": false
                                },
                                "icon_align": "right",
                                "icon_space": {
                                    "unit": "px",
                                    "size": 0,
                                    "sizes": []
                                },
                                "content_background_color": "#F5F7FA",
                                "content_typography_typography": "custom",
                                "content_typography_font_family": "Poppins",
                                "content_typography_font_weight": "400",
                                "content_padding": {
                                    "unit": "px",
                                    "top": "10",
                                    "right": "25",
                                    "bottom": "25",
                                    "left": "25",
                                    "isLinked": false
                                },
                                "_animation": "fadeInUp",
                                "__globals__": {
                                    "tab_active_color": "globals\/colors?id=e28396d"
                                }
                            },
                            "elements": [],
                            "isInner": false,
                            "widgetType": "toggle",
                            "elType": "widget"
                        }
                    ],
                    "isInner": false,
                    "elType": "column"
                }
            ],
            "isInner": false,
            "elType": "section"
        },
        {
            "id": "f1e3c43",
            "settings": {
                "margin": {
                    "unit": "em",
                    "top": "2",
                    "right": 0,
                    "bottom": "7",
                    "left": 0,
                    "isLinked": false
                },
                "overflow": "hidden",
                "border_radius_mobile": {
                    "unit": "px",
                    "top": "42",
                    "right": "42",
                    "bottom": "42",
                    "left": "42",
                    "isLinked": true
                },
                "margin_mobile": {
                    "unit": "em",
                    "top": "3",
                    "right": 0,
                    "bottom": "3",
                    "left": 0,
                    "isLinked": false
                },
                "padding_mobile": {
                    "unit": "px",
                    "top": "0",
                    "right": "10",
                    "bottom": "0",
                    "left": "10",
                    "isLinked": false
                }
            },
            "elements": [
                {
                    "id": "2aef211d",
                    "settings": {
                        "_column_size": 100,
                        "_inline_size": null,
                        "background_background": "classic",
                        "background_image": {
                            "url": "https:\/\/template-kit.rootlayers.com\/portosia\/wp-content\/uploads\/sites\/4\/2020\/10\/circle-big.png",
                            "id": 98
                        },
                        "background_position": "initial",
                        "background_position_tablet": "initial",
                        "background_position_mobile": "initial",
                        "background_xpos": {
                            "unit": "px",
                            "size": 778,
                            "sizes": []
                        },
                        "background_xpos_tablet": {
                            "unit": "px",
                            "size": 422,
                            "sizes": []
                        },
                        "background_xpos_mobile": {
                            "unit": "px",
                            "size": 49,
                            "sizes": []
                        },
                        "background_ypos": {
                            "unit": "px",
                            "size": 240,
                            "sizes": []
                        },
                        "background_ypos_tablet": {
                            "unit": "px",
                            "size": 248,
                            "sizes": []
                        },
                        "background_ypos_mobile": {
                            "unit": "px",
                            "size": 339,
                            "sizes": []
                        },
                        "background_repeat": "no-repeat",
                        "border_radius": {
                            "unit": "px",
                            "top": "62",
                            "right": "62",
                            "bottom": "62",
                            "left": "62",
                            "isLinked": true
                        },
                        "padding": {
                            "unit": "em",
                            "top": "8",
                            "right": "3",
                            "bottom": "9",
                            "left": "3",
                            "isLinked": false
                        },
                        "padding_mobile": {
                            "unit": "em",
                            "top": "7",
                            "right": "1",
                            "bottom": "8",
                            "left": "1",
                            "isLinked": false
                        },
                        "__globals__": {
                            "background_color": "globals\/colors?id=e28396d"
                        }
                    },
                    "elements": [
                        {
                            "id": "1287f498",
                            "settings": {
                                "image": {
                                    "url": "https:\/\/template-kit.rootlayers.com\/portosia\/wp-content\/uploads\/sites\/4\/2020\/10\/circle-purple.png",
                                    "id": 100
                                },
                                "motion_fx_motion_fx_mouse": "yes",
                                "motion_fx_mouseTrack_effect": "yes",
                                "motion_fx_mouseTrack_speed": {
                                    "unit": "px",
                                    "size": 0.59999999999999997779553950749686919152736663818359375,
                                    "sizes": []
                                },
                                "_animation": "fadeIn",
                                "_element_width": "auto",
                                "_position": "absolute",
                                "_offset_x": {
                                    "unit": "px",
                                    "size": 13,
                                    "sizes": []
                                },
                                "_offset_orientation_v": "end",
                                "_offset_y_end": {
                                    "unit": "px",
                                    "size": 15,
                                    "sizes": []
                                }
                            },
                            "elements": [],
                            "isInner": false,
                            "widgetType": "image",
                            "elType": "widget"
                        },
                        {
                            "id": "4b80111a",
                            "settings": {
                                "image": {
                                    "url": "https:\/\/template-kit.rootlayers.com\/portosia\/wp-content\/uploads\/sites\/4\/2020\/10\/circle-pink.png",
                                    "id": 99
                                },
                                "motion_fx_motion_fx_mouse": "yes",
                                "motion_fx_mouseTrack_effect": "yes",
                                "motion_fx_mouseTrack_direction": "negative",
                                "motion_fx_mouseTrack_speed": {
                                    "unit": "px",
                                    "size": 0.5,
                                    "sizes": []
                                },
                                "_animation": "fadeIn",
                                "_element_width": "auto",
                                "_position": "absolute",
                                "_offset_orientation_h": "end",
                                "_offset_x_end": {
                                    "unit": "px",
                                    "size": 93.099999999999994315658113919198513031005859375,
                                    "sizes": []
                                },
                                "_offset_y": {
                                    "unit": "px",
                                    "size": -52,
                                    "sizes": []
                                }
                            },
                            "elements": [],
                            "isInner": false,
                            "widgetType": "image",
                            "elType": "widget"
                        },
                        {
                            "id": "e386651",
                            "settings": {
                                "image": {
                                    "url": "https:\/\/template-kit.rootlayers.com\/portosia\/wp-content\/uploads\/sites\/4\/2020\/10\/round-grey.png",
                                    "id": 11
                                },
                                "motion_fx_motion_fx_mouse": "yes",
                                "motion_fx_mouseTrack_effect": "yes",
                                "motion_fx_mouseTrack_direction": "negative",
                                "motion_fx_mouseTrack_speed": {
                                    "unit": "px",
                                    "size": 0.299999999999999988897769753748434595763683319091796875,
                                    "sizes": []
                                },
                                "_animation": "fadeInUp",
                                "_element_width": "auto",
                                "_position": "absolute",
                                "_offset_x": {
                                    "unit": "px",
                                    "size": 393,
                                    "sizes": []
                                },
                                "_offset_orientation_v": "end",
                                "_offset_y_end": {
                                    "unit": "px",
                                    "size": 83,
                                    "sizes": []
                                }
                            },
                            "elements": [],
                            "isInner": false,
                            "widgetType": "image",
                            "elType": "widget"
                        },
                        {
                            "id": "4072e6a7",
                            "settings": {
                                "image": {
                                    "url": "https:\/\/template-kit.rootlayers.com\/portosia\/wp-content\/uploads\/sites\/4\/2020\/10\/round-grey.png",
                                    "id": 11
                                },
                                "space": {
                                    "unit": "px",
                                    "size": 10,
                                    "sizes": []
                                },
                                "motion_fx_motion_fx_mouse": "yes",
                                "motion_fx_mouseTrack_effect": "yes",
                                "_animation": "fadeInDown",
                                "_element_width": "auto",
                                "_position": "absolute",
                                "_offset_x": {
                                    "unit": "px",
                                    "size": 538,
                                    "sizes": []
                                },
                                "_offset_y": {
                                    "unit": "px",
                                    "size": -31,
                                    "sizes": []
                                }
                            },
                            "elements": [],
                            "isInner": false,
                            "widgetType": "image",
                            "elType": "widget"
                        },
                        {
                            "id": "50e525b",
                            "settings": {
                                "title": "Interested Working<br>With me? Let's connect!",
                                "align": "center",
                                "title_color": "#FFFFFF",
                                "typography_typography": "custom",
                                "typography_font_family": "Poppins",
                                "typography_font_size": {
                                    "unit": "px",
                                    "size": 60,
                                    "sizes": []
                                },
                                "typography_font_size_tablet": {
                                    "unit": "px",
                                    "size": 42,
                                    "sizes": []
                                },
                                "typography_font_weight": "600",
                                "typography_line_height": {
                                    "unit": "em",
                                    "size": 1.399999999999999911182158029987476766109466552734375,
                                    "sizes": []
                                },
                                "_z_index": 1,
                                "_animation": "fadeInDown"
                            },
                            "elements": [],
                            "isInner": false,
                            "widgetType": "heading",
                            "elType": "widget"
                        },
                        {
                            "id": "3badac9c",
                            "settings": {
                                "text": "Contact Me",
                                "align": "center",
                                "size": "xl",
                                "typography_typography": "custom",
                                "typography_font_family": "Poppins",
                                "typography_font_size": {
                                    "unit": "px",
                                    "size": 16,
                                    "sizes": []
                                },
                                "typography_font_weight": "500",
                                "background_color": "#FFFFFF",
                                "hover_animation": "float",
                                "border_radius": {
                                    "unit": "px",
                                    "top": "15",
                                    "right": "15",
                                    "bottom": "15",
                                    "left": "15",
                                    "isLinked": true
                                },
                                "_margin": {
                                    "unit": "px",
                                    "top": "30",
                                    "right": "0",
                                    "bottom": "0",
                                    "left": "0",
                                    "isLinked": false
                                },
                                "_z_index": 1,
                                "_animation": "fadeInUp",
                                "__globals__": {
                                    "button_text_color": "globals\/colors?id=e28396d"
                                }
                            },
                            "elements": [],
                            "isInner": false,
                            "widgetType": "button",
                            "elType": "widget"
                        }
                    ],
                    "isInner": false,
                    "elType": "column"
                }
            ],
            "isInner": false,
            "elType": "section"
        }
    ],
    "page_settings": {
        "hide_title": "yes"
    }
}